{"这个": 10, "世界": 7, "最好": 5, "动画片": 26, "这是": 2, "一只": 1, "安卓": 1, "苹果": 1, "故事": 9, "所有": 5, "东西": 3, "eva": 7, "乡下": 3, "文艺": 1, "小伙儿": 1, "追求": 4, "都市": 1, "精英": 1, "以及": 3, "很久没": 1, "看过": 4, "这么": 8, "可爱": 24, "瓦力": 43, "什么": 3, "不会": 3, "除了": 2, "一声声": 1, "执拗": 1, "Eve": 1, "他们": 4, "星空": 2, "画出": 1, "美丽": 5, "弧线": 1, "无意间": 1, "守候": 1, "一份": 2, "真正": 1, "爱情": 16, "再也": 1, "没有": 14, "美的": 4, "谈到": 1, "Wall": 6, "来源": 1, "导演": 2, "安德鲁": 1, "斯坦顿": 1, "否认": 1, "ET": 1, "或者": 2, "霹雳": 1, "五号": 1, "说法": 2, "尽管": 1, "外形": 2, "承认": 1, "自己": 3, "创造": 1, "受到": 1, "台灯": 1, "Luxo": 1, "双筒": 1, "望远镜": 1, "R2": 1, "D2": 1, "迪士尼": 1, "乐园": 1, "之旅": 1, "机器人": 28, "卓别林": 1, "伍迪": 2, "艾伦": 2, "影响": 1, "引进": 1, "真是太": 3, "遗憾": 2, "人类": 10, "片子": 7, "里面": 6, "处于": 2, "完全": 5, "嘲笑": 2, "位置": 2, "其实": 4, "应该": 3, "美国": 4, "片中": 1, "超大型": 1, "连锁": 1, "企业": 1, "BNL": 1, "未来": 4, "已经": 5, "统一": 1, "商业": 1, "领域": 1, "堕落": 1, "依靠": 1, "电脑": 2, "帮助": 1, "才能": 1, "吃喝拉撒": 1, "胖子": 1, "而且": 1, "从小": 1, "接受": 1, "教育": 3, "消费": 3, "快点": 1, "虽然": 5, "Matrix": 1, "灰暗": 1, "但是": 6, "相差不远": 1, "并非": 1, "丧失": 1, "本性": 1, "只是": 6, "遗忘": 1, "而已": 1, "Eva": 3, "出现": 1, "提醒": 1, "还有": 4, "一个": 6, "满目疮痍": 1, "等待": 1, "回归": 1, "陈奕迅": 1, "唱歌": 1, "人生": 5, "准备": 1, "第二遍": 1, "清纯": 1, "少男": 1, "前卫": 1, "暴力": 1, "冰美人": 1, "爱情故事": 5, "xixi": 1, "地球": 9, "最后": 3, "一個": 1, "收納": 1, "歸類": 1, "walle": 4, "應該": 1, "巨蟹座": 1, "浪漫": 6, "一塌糊涂": 1, "废墟": 1, "开出": 1, "牵手": 2, "散步": 1, "下午": 1, "世上": 1, "伟大": 2, "機器": 1, "談戀": 1, "愛也": 1, "避免": 1, "不了": 1, "男女搭配": 1, "窠臼": 1, "有夠": 1, "諷刺": 1, "不用": 1, "造型": 1, "...": 5, "人類": 1, "想象力": 2, "其實": 1, "貧瘠": 1, "那么": 12, "一丝": 1, "感人": 12, "皮克斯": 6, "不算": 1, "精彩": 2, "属于": 1, "那种": 4, "背景": 2, "深刻": 2, "剧情": 5, "简单": 4, "豆瓣": 4, "堪称": 1, "完美": 2, "动画": 13, "作品": 2, "能吐句": 1, "好弱": 1, "Just": 1, "need": 1, "someone": 1, "who": 1, "will": 1, "look": 1, "after": 1, "you": 1, "一股脑儿": 1, "五星": 1, "很傻": 1, "很酷": 1, "到底": 1, "多少": 1, "是因为": 1, "总动员": 2, "译名": 2, "错过": 1, "出色": 1, "一部": 10, "不到": 1, "替代品": 1, "默片": 3, "看似": 1, "非常复杂": 1, "设计": 1, "怎么": 4, "乡村": 1, "屌丝": 2, "恋上": 1, "城里": 1, "白富": 3, "整部": 2, "影片": 3, "既有": 1, "幽默": 2, "搞笑": 1, "感动": 19, "地方": 3, "印象": 2, "还是": 5, "那个": 4, "强迫症": 2, "清洁": 2, "真的": 12, "同时": 2, "这部": 8, "教会": 1, "我们": 5, "保护": 2, "绿化": 1, "重要性": 1, "具有": 1, "意义": 7, "情话": 1, "知道": 5, "喜欢": 22, "总共": 1, "起来": 1, "几句": 3, "台词": 8, "懒散": 1, "舰长": 1, "真谛": 1, "不要": 5, "生存": 5, "要家": 1, "事情": 2, "那小": 1, "眼神": 1, "动画电影": 6, "伊娃": 17, "太空": 8, "滑翔": 2, "那段": 4, "温暖": 6, "捡起": 2, "记忆卡": 2, "想起": 2, "时候": 5, "好感": 4, "泪目": 2, "技术": 1, "似乎": 2, "Ratatouille": 2, "出彩": 1, "ILM": 1, "帮忙": 1, "一直": 3, "Pixar": 2, "强项": 1, "回想": 1, "叫板": 1, "本身": 1, "点缀": 1, "有些": 4, "寒碜": 1, "片尾": 1, "一把": 1, "2D": 1, "有点": 4, "美术": 1, "致敬": 2, "味道": 1, "本片": 1, "一项": 1, "安尼奖": 1, "没拿到": 1, "当年": 2, "可是": 1, "横扫": 1, "九项": 1, "Remy": 1, "爱哈": 1, "超级": 2, "我得静": 1, "会儿": 1, "不行": 1, "啊啊啊": 4, "感情": 5, "努力": 1, "单纯": 3, "诚挚": 1, "十分": 1, "有关": 2, "环保": 4, "科技": 3, "电影": 18, "若干年": 1, "环境": 1, "破坏": 1, "清理": 1, "遭遇": 2, "展现": 2, "环境污染": 1, "通过": 1, "公理": 1, "讲述": 2, "因为": 1, "发展": 1, "变得": 1, "慵懒": 1, "可以": 7, "带来": 2, "便利": 1, "问题": 1, "两个": 3, "之间": 2, "唯美": 1, "温馨": 1, "纯情": 1, "有时": 1, "觉得": 5, "无力": 1, "总是": 2, "老少皆宜": 1, "脑洞": 1, "大开": 1, "收藏": 1, "小屋": 1, "古老": 1, "唱片": 1, "小强": 2, "牵线": 1, "哈哈": 2, "飞船": 2, "机器": 4, "卫士": 1, "好萌": 4, "不过": 2, "初衷": 1, "呼吁": 1, "人们": 1, "珍惜": 3, "资源": 1, "好看": 18, "放弃": 1, "精神": 2, "竟然": 3, "熬过": 1, "处理": 1, "垃圾": 2, "时间": 1, "日子": 1, "过得": 1, "有意思": 2, "收集": 1, "小东西": 1, "每个": 3, "卓尔不群": 1, "don": 1, "want": 2, "to": 2, "survive": 1, "live": 1, "轻松": 1, "有趣": 3, "全程": 1, "笑个": 1, "不停": 1, "科幻": 2, "色彩": 1, "浓厚": 1, "如果": 2, "DVD": 1, "画面": 3, "不像": 2, "想象": 2, "细节": 4, "歌曲": 1, "好听": 1, "冰冷": 1, "不乏": 1, "温情": 2, "就是": 3, "魅力": 1, "本来": 1, "拒绝": 1, "配音": 1, "意外": 1, "感觉": 3, "很萌": 1, "一般": 5, "居然": 2, "理解": 1, "非常": 6, "优秀": 1, "经典": 8, "生命": 1, "无关": 1, "萌萌": 2, "找到": 2, "真爱": 1, "如此": 1, "动人": 2, "特别": 5, "呼唤": 1, "名字": 3, "无法": 3, "言语": 1, "传达": 1, "喜爱": 1, "永远": 2, "纯纯": 1, "向往": 1, "渴望": 1, "动漫": 3, "果然": 1, "成年人": 1, "欢乐": 1, "中伴": 1, "泪水": 1, "最爱": 1, "守护者": 1, "相比": 1, "来说": 1, "无聊": 1, "值得": 4, "深思": 2, "深意": 1, "wall": 7, "不必": 1, "蓝色": 1, "孤独": 4, "简直": 1, "梦幻": 1, "我要": 3, "活得": 4, "瓦利": 1, "五分钟": 1, "哈哈哈哈": 2, "哈哈哈": 2, "WALL": 3, "美好": 7, "人格": 1, "象征": 1, "陪伴": 2, "一次": 6, "神剧": 1, "明明": 2, "情节": 3, "还会": 1, "跟着": 1, "不仅仅": 1, "孩子": 3, "童话": 1, "即便": 1, "精湛": 1, "特效": 2, "依旧": 1, "一场": 2, "足以": 1, "直抵": 1, "心灵": 1, "佳作": 1, "环境保护": 1, "立意": 1, "乌托邦": 1, "反讽": 1, "宏观": 1, "之下": 2, "落足": 1, "令人": 1, "看到": 5, "生活": 3, "执着": 2, "追寻": 1, "天堂": 1, "敞开": 1, "闭上": 1, "双眼": 1, "玫瑰": 2, "贴近": 1, "心房": 1, "身处": 1, "那里": 1, "遍地": 1, "怒放": 1, "开口": 1, "说话": 1, "天使": 1, "便会": 1, "歌唱": 1, "平凡": 1, "语言": 1, "情歌": 1, "重要": 1, "三遍": 1, "最长": 1, "告白": 1, "几年": 1, "兼具": 1, "日本": 1, "美式": 1, "之一": 1, "过多": 1, "吸引": 2, "一段": 1, "太美": 1, "九十分钟": 1, "友谊": 1, "冒险": 1, "英雄": 1, "反抗": 1, "宣扬": 1, "理念": 1, "播撒": 1, "理想主义": 1, "绿色": 1, "种子": 1, "童真": 1, "惊险": 1, "不得不": 1, "热土": 1, "孕育": 1, "成长": 1, "PS": 1, "片尾曲": 1, "两分钟": 1, "简笔": 1, "漫画": 2, "看头": 1, "成人": 1, "讽刺": 3, "意味": 1, "十足": 2, "一副": 1, "一样": 5, "进化": 1, "成猪": 1, "生物": 1, "肥胖": 1, "脑萎缩": 1, "猪脑": 1, "大小": 1, "好多": 2, "反应": 1, "智能": 1, "控制": 1, "例外": 1, "思索": 1, "可能": 2, "天马行空": 1, "表面": 1, "根本无法": 1, "掩盖": 1, "深厚": 1, "内涵": 1, "多年": 1, "唯一": 1, "巅峰": 1, "之作": 1, "制作": 1, "无可挑剔": 1, "开场": 1, "尘土飞扬": 1, "场景": 1, "极具": 1, "质感": 1, "相当": 2, "难得": 1, "挺不错": 2, "保护环境": 1, "迫在眉睫": 1, "en": 1, "好久": 1, "优质": 1, "大片": 1, "活泼可爱": 1, "好好": 2, "国内": 1, "多出": 1, "23": 1, "来看": 1, "第一部": 1, "太有": 1, "励志": 1, "声音": 1, "后面": 2, "好怕": 1, "突然": 1, "消失": 1, "随着": 1, "年龄": 1, "增长": 1, "不太": 1, "偶然": 1, "之后": 1, "趣味": 1, "心中": 2, "最棒": 1, "永恒": 2, "在外": 1, "灭火器": 1, "示爱": 1, "飞行": 1, "心底": 1, "中文": 1, "全片": 1, "看着": 1, "外表": 2, "破旧": 2, "独自": 1, "守护": 1, "荒废": 1, "眼睛": 1, "塑造": 1, "出来": 2, "苍凉": 1, "孤独感": 1, "心疼": 1, "不已": 1, "确实": 1, "满满": 1, "认认真真": 1, "拾掇": 1, "那些": 2, "宝贝": 1, "无非": 1, "瓶瓶罐罐": 1, "一次性": 1, "叉子": 1, "等等": 1, "眼中": 1, "废品": 1, "懂得": 1, "多么": 3, "无论": 2, "物质": 1, "情感": 2, "遇到": 1, "幸福": 3, "演绎": 1, "篇章": 1, "退化": 1, "WALLE": 2, "浑身": 1, "散发": 1, "遥远": 1, "星球": 1, "泥土": 1, "成功": 1, "女神": 1, "最高": 1, "代表作品": 1, "珠圆玉润": 1, "身怀绝技": 1, "EWA": 1, "评分": 1, "小时候": 1, "画风": 1, "前半段": 1, "寂寞": 1, "规律": 1, "很大": 1, "意见": 1, "这种": 3, "延续下去": 1, "后半段": 2, "落入": 1, "俗套": 1, "尤其": 1, "模型": 1, "稍微": 1, "协调": 1, "冷冷的": 1, "比谈": 1, "恋爱": 1, "更让人": 1, "棒棒": 2, "永不": 1, "褪色": 1, "龙族": 1, "老实": 1, "低低的": 1, "EVE": 1, "希望": 1, "这样": 1, "一天": 1, "到来": 1, "20160619": 1, "上海": 1, "电影节": 1, "展映": 1, "终于": 3, "银幕": 3, "巨幕版": 1, "我会": 1, "没想到": 1, "断断续续": 1, "20": 2, "多分钟": 1, "痛哭流涕": 1, "直击": 1, "我心": 1, "很多": 2, "容易": 1, "忽视": 1, "2001": 1, "明晰": 1, "总之": 1, "上能": 1, "六星": 1, "神作": 2, "不管": 1, "哪里": 1, "然后": 1, "牵着": 1, "一起": 2, "萌死": 1, "超萌超": 2, "羡慕": 1, "宇宙": 1, "强大": 1, "爆发": 2, "......": 1, "Walle": 1, ".......": 1, "世间": 1, "不过如此": 1, "还要": 1, "这句": 1, "PROPER": 1, "DVDRiP": 1, "XViD": 1, "BenBurtt": 1, "暖心": 1, "极致": 1, "好几遍": 1, "现在": 1, "几乎": 1, "短片": 1, "伊瓦": 1, "我爱你": 1, "推荐": 1, "beyond": 1, "perfection": 1, "留下": 1, "不深": 1, "之爱": 1, "始于": 1, "一刻": 1, "游戏": 1, "挺好玩": 1, "差到": 1, "哪儿": 1, "2008": 1, "漫游": 1, "结尾": 1, "迪斯尼": 2, "却是": 1, "强烈推荐": 1, "观看": 1, "不愧为": 1, "重温": 1, "感慨": 1, "绝对": 1, "心头": 1, "高中": 1, "同学": 1, "mp4": 1, "如痴如醉": 1, "击中": 1, "看不下去": 1, "太漂亮": 1, "很漂亮": 1, "太赞": 1, "前一阵子": 1, "第十": 1, "放映室": 1, "介绍": 1, "此片": 1, "定义": 1, "灾难片": 1, "另类": 1, "某些": 1, "三星": 1, "产品": 1, "老套": 3, "类型": 1, "看得": 1, "太多": 1, "实在": 2, "有够": 1, "厌倦": 1, "love": 1, "hope": 1, "forever": 1, "辐射": 1, "风格": 1, "真实": 1, "太棒了": 1, "巨萌": 1, "无需": 1, "多言": 1, "俗不可耐": 1, "一偿": 1, "看一遍": 1, "心愿": 1, "卡通化": 1, "新世界": 1, "乐观": 1, "破碎": 1, "之心": 1, "结局": 1, "太仓促": 1, "pk": 1, "过太多": 1, "08": 4, "情侣": 1, "矫情": 1, "吊足味口": 1, "任何": 1, "佩服": 1, "想法": 1, "超棒": 1, "艾娃": 1, "不是": 2, "而是": 1, "独有": 1, "野蛮女友": 2, "痴情": 2, "粗犷": 1, "秀气": 1, "流线型": 1, "女性化": 1, "eve": 3, "E通": 1, "个人": 1, "英雄主义": 1, "牺牲": 1, "赢得": 1, "好奇": 1, "繁华": 1, "样子": 1, "宣传片": 1, "烛光": 1, "打动": 1, "基本": 1, "元素": 1, "萝卜": 1, "谈恋爱": 1, "滚蛋": 1, "呵呵": 1, "wa": 1, "..": 2, "li": 1, "....": 1, "超越": 2, "原来": 1, "mark": 1, "偷偷": 1, "rewind": 1, "backup": 1, "洁癖": 1, "mo": 3, "更萌": 1, "前半部": 1, "眼泪汪汪": 1, "治愈": 1, "打招呼": 1, "萌哭": 1, "好玩": 1, "颠覆": 1, "猜测": 1, "爱护": 1, "人人有责": 1, "未来派": 1, "穷小子": 1, "爱上": 1, "富家女": 1, "想握": 1, "女孩儿": 1, "觸動": 1, "傷感": 1, "反思": 1, "萌屎": 1, "会心一笑": 1, "流泪": 1, "说不出来": 1, "最最": 1, "纯粹": 1, "精致": 1, "轻松愉快": 1, "pix": 1, "常在": 1, "铁皮": 1, "乍看": 1, "其貌不扬": 1, "以小见大": 1, "之余": 1, "惊叹": 1, "好莱坞": 1, "表现力": 1, "几颗": 1, "当时": 1, "天空": 2, "漂浮": 1, "尘埃": 1, "EVA": 2, "表弟": 1, "热泪盈眶": 1, "轻喜剧": 1, "电影学院": 1, "十佳": 10, "纽约": 4, "影评人": 4, "协会": 5, "最佳": 3, "洛杉矶": 1, "最佳影片": 2, "华盛顿": 1, "国家": 1, "评论": 1, "年度": 9, "波士顿": 1, "时代": 1, "NO.1": 2, "滚石": 1, "NO.5": 1, "NO.2": 2, "NO.6": 1, "邮报": 1, "NO.3": 2, "纽约时报": 2, "斯科特": 1, "斯蒂芬": 2, "霍尔": 1, "罗杰": 1, "艾伯特": 1, "佳片": 1, "重看": 1, "真心": 1, "那纯": 1, "白云": 1, "So": 1, "cute": 1, "full": 1, "of": 1, "humanity": 1, "ps": 1, "吹神": 1, "七百年": 1, "丽江": 1, "路上": 1, "半星": 1, "MO": 1, "门当户对": 1, "这些": 1, "以后": 1}