{"除了": 2, "JohnnyDepp": 6, "那样": 5, "眼神": 20, "就让": 1, "相信": 2, "全世界": 1, "爱德华": 74, "有时候": 2, "卑劣": 1, "人性": 3, "剪刀": 5, "眼睛": 2, "心疼": 4, "经典": 8, "一部": 10, "美丽": 5, "童话": 43, "那个": 7, "孤独": 23, "至少": 3, "两遍": 1, "本是": 2, "生命": 3, "常态": 4, "完全": 5, "感觉": 8, "情绪": 3, "酝酿": 1, "结束": 3, "失望": 1, "美好": 13, "现实": 7, "聒噪": 1, "奇怪": 2, "喜欢": 22, "这么": 5, "竟然": 3, "不到": 2, "共鸣": 1, "Adward": 1, "脆弱": 4, "永远": 12, "忘不掉": 1, "第一页": 1, "显示": 1, "出来": 6, "影评": 2, "恶心": 1, "滥情": 1, "悲哀": 1, "写成": 1, "剧情": 4, "介绍": 1, "蒂姆": 19, "伯顿": 11, "电影": 34, "大部分": 2, "人物": 4, "智商": 3, "负值": 1, "如果": 23, "没有": 31, "不能": 29, "保护": 11, "拥抱": 31, "这个": 21, "城市": 2, "看不到": 2, "一场": 5, "一片": 2, "雪花": 14, "落地": 2, "我爱你": 6, "现在": 10, "已经": 7, "老妇人": 1, "记得": 6, "当初": 1, "样子": 5, "东西": 6, "注定": 9, "只能": 7, "潜藏在": 1, "角落": 2, "每个": 2, "初恋": 1, "时候": 28, "佩格": 7, "居住": 1, "小镇": 4, "画笔": 1, "彩色": 2, "这里": 2, "人们": 4, "好奇": 1, "热情": 1, "多疑": 1, "获得": 1, "明星": 1, "般的": 4, "关注": 1, "人类": 12, "世界": 23, "遭遇": 1, "讨伐": 1, "对于": 3, "冰雕": 4, "女神像": 1, "无法": 24, "守护": 1, "完美": 3, "悲剧": 9, "如同": 1, "后来": 5, "每年": 1, "当年": 3, "还是": 22, "字幕版": 1, "英文": 1, "不是": 10, "很会": 1, "真的": 9, "就是": 16, "表演": 3, "出色": 2, "片子": 13, "启蒙": 1, "CCTV6": 2, "爱上": 6, "从此": 2, "改变": 4, "2002.2": 1, "cctv6": 1, "佳片": 2, "浪漫": 7, "忧郁": 11, "成人": 5, "忧伤": 1, "Johnny": 10, "Depp": 12, "他来": 2, "之前": 6, "从不": 2, "下雪": 7, "这片": 2, "居然": 4, "修复": 1, "即使": 2, "TB": 1, "作品": 6, "纯真": 7, "发明家": 1, "Ed": 1, "弄坏了": 1, "原本": 1, "作为": 3, "圣诞礼物": 2, "人造": 1, "试图": 1, "抚摸": 1, "至亲": 1, "留下": 3, "血痕": 1, "泪点": 2, "想不到": 1, "这次": 1, "边上": 1, "有人": 3, "几乎": 3, "同时": 1, "开哭": 1, "而且": 1, "大声": 1, "灯亮": 1, "之后": 2, "发现": 6, "清朗": 1, "白发": 1, "大叔": 2, "可爱": 5, "与非": 1, "只有": 11, "一家": 1, "因为": 14, "那么": 9, "双手": 10, "明明": 3, "善良": 16, "想救": 1, "最终": 3, "却成": 2, "伤害": 6, "最爱": 1, "寂寞": 7, "眼泪": 1, "哗啦啦": 1, "传递": 1, "感情": 3, "动容": 1, "我用": 2, "用刀": 2, "当时": 5, "感动": 10, "感到": 2, "无比": 1, "不公": 1, "为什么": 9, "得到": 1, "属于": 5, "自己": 13, "冰冷": 4, "残酷": 1, "无情": 1, "总是": 6, "心意": 1, "怎么样": 2, "我们": 4, "坚强": 1, "JOHN": 1, "DEPP": 4, "经典之作": 3, "惊醒": 1, "一个": 29, "完成": 1, "小学": 2, "六年级": 1, "电影频道": 3, "感受": 4, "满脸": 1, "疤痕": 1, "他帅": 1, "性感": 1, "风骚": 1, "邻居": 2, "女老师": 1, "阿姨": 2, "姐姐": 1, "勾搭": 1, "开心": 1, "三星": 1, "年代": 4, "堪称": 1, "包括": 1, "题材": 2, "依然": 5, "不过": 8, "庆幸": 1, "碰到": 1, "家人": 1, "真正": 6, "该是": 1, "多么": 4, "伤心": 2, "纯粹": 1, "本该": 1, "幸福": 1, "一生": 3, "大哭": 1, "身上": 2, "表现": 2, "渴望": 2, "沟通": 1, "使得": 1, "无论": 2, "外表": 2, "久违": 1, "一种": 4, "温暖": 7, "其实": 10, "所有": 2, "刻骨铭心": 1, "悲欢": 1, "伤痛": 2, "可以": 10, "避免": 1, "只是": 3, "选择": 2, "沉沦": 1, "小时候": 2, "相爱": 4, "一起": 6, "年迈": 1, "默默": 2, "怀念": 1, "仍然": 2, "那种": 7, "偏要": 1, "性格": 2, "Hold": 5, "me": 7, "can": 4, "童话故事": 4, "德普": 30, "最后": 8, "害怕": 1, "相处": 1, "不舍": 1, "善变": 1, "勇敢": 1, "踏出": 1, "第一步": 1, "才能": 4, "不同": 4, "最好": 3, "短片": 2, "拍长片": 2, "讲故事": 2, "能力": 2, "似乎": 3, "有所": 2, "下降": 2, "通过": 3, "演员": 4, "场景": 2, "淋漓尽致": 3, "表达出来": 2, "所以": 2, "这部": 18, "迷恋": 2, "查理": 1, "巧克力": 1, "工厂": 1, "开始": 7, "童话般": 3, "爱情": 30, "算是": 1, "经典影片": 1, "而是": 2, "面前": 2, "大胆": 1, "奔放": 1, "天马行空": 1, "服化": 1, "无不": 1, "浸透": 1, "伯顿式": 1, "奇思妙想": 1, "拥有": 6, "一双": 11, "剪刀手": 35, "...": 12, "出场": 1, "形象": 3, "有点": 5, "重点": 2, "后面": 3, "男女": 2, "走进": 3, "人心": 1, "充满": 4, "温情": 2, "片起": 1, "为此": 1, "烂片": 1, "故事": 20, "简单": 4, "带点": 1, "哥特式": 3, "风格": 7, "唯美": 6, "十足": 1, "好友": 1, "推荐": 3, "一般": 4, "男主": 1, "据说": 1, "海盗王": 1, "主角": 2, "妆化": 1, "爱情故事": 4, "佩服": 2, "编剧": 1, "导演": 4, "想象力": 4, "感人": 5, "残酷无情": 1, "难忘": 2, "或许": 5, "听见": 1, "这样": 9, "也许": 6, "本来": 1, "不少": 1, "温柔": 4, "今天": 2, "小雪": 1, "马上": 1, "就要": 1, "进入": 1, "飘雪": 2, "季节": 1, "卡索里": 1, "还好": 1, "屋顶": 1, "阁楼": 1, "不会": 10, "保证": 1, "从今以后": 1, "每次": 4, "看到": 8, "落雪": 1, "想念": 1, "一次": 8, "晚安": 1, "赞叹": 1, "薇诺娜": 9, "美貌": 1, "搭配": 1, "哥特": 4, "气质": 1, "还有": 11, "他们": 8, "那段": 1, "非常": 6, "约翰尼": 10, "需要": 1, "心灵": 4, "动作": 2, "诠释": 2, "手握": 1, "的话": 2, "鬼斧神功": 1, "大鱼": 2, "一样": 9, "古怪": 2, "波顿": 8, "如今": 2, "剩下": 1, "再长": 1, "半个": 1, "小时": 1, "更好": 2, "一直": 4, "无感": 4, "令人": 4, "心碎": 2, "跨越": 1, "障碍": 1, "解决": 1, "问题": 1, "撕碎": 1, "这累": 1, "比较": 2, "特别": 5, "这种": 2, "容易": 2, "未必": 2, "绽放": 2, "觉得": 9, "这句": 1, "概括": 1, "看着": 2, "可怕": 2, "凶悍": 1, "内心": 6, "柔软": 2, "说话": 1, "语气": 1, "原来": 6, "好似": 1, "出名": 1, "特效": 1, "化妆": 1, "造型": 4, "布景": 2, "设计": 1, "配乐": 3, "极佳": 1, "出彩": 1, "遗憾": 2, "老套": 1, "配角": 1, "程式化": 1, "不忍": 1, "直视": 1, "寓言": 1, "高潮": 1, "结尾": 2, "烂俗": 2, "理解": 3, "铺垫": 1, "没到": 2, "顶点": 1, "戛然而止": 1, "打动": 2, "7.5": 1, "10": 1, "fake": 1, "plastic": 1, "earth": 1, "..": 1, "90": 3, "很久以前": 1, "珍重": 1, "各种": 2, "情谊": 1, "扮演": 1, "估计": 1, "影迷": 2, "这段": 1, "哭泣": 2, "可能": 3, "有着": 6, "健全": 1, "身体": 1, "缺陷": 1, "却是": 2, "清澈": 1, "明亮": 1, "但是": 11, "庸俗": 2, "意味着": 1, "悲惨": 2, "结局": 10, "机器人": 12, "尼德": 2, "早期": 1, "情节": 6, "紧凑": 1, "时隔": 1, "遥远": 2, "有些": 3, "模糊": 1, "找个": 1, "时间": 1, "重温": 5, "一遍": 3, "好看": 4, "伤感": 2, "多次": 2, "值得": 1, "悲伤": 5, "抱抱": 2, "少年": 1, "一点": 2, "海盗": 2, "船长": 3, "是不是": 3, "张脸": 1, "来演": 1, "20": 1, "多年": 1, "镜头": 2, "语音": 1, "画面": 2, "构图": 1, "等等": 1, "记不得": 1, "第几次": 1, "或者": 1, "同学": 1, "生动": 1, "无辜": 2, "任何": 2, "JD": 2, "百分百": 1, "理由": 2, "永恒": 1, "本命": 1, "感慨": 1, "曾经": 6, "般配": 1, "一对": 1, "佳偶": 1, "戴普": 2, "心智": 2, "生活": 3, "古堡": 9, "闯入": 2, "化妆品": 2, "推销员": 2, "带回家": 2, "单纯": 11, "女儿": 2, "瑞德": 5, "慢慢": 2, "吸引": 2, "突然": 2, "想到": 4, "泰戈尔": 1, "写给": 1, "林徽因": 1, "徐志摩": 1, "这首": 1, "天空": 2, "蔚蓝": 1, "大地": 1, "碧绿": 1, "经过": 2, "它们": 1, "微风": 1, "初中": 1, "看过": 4, "我学": 1, "园林": 1, "希望": 7, "厉害": 1, "导致": 1, "死亡": 1, "之间": 3, "多点": 1, "信任": 2, "正常": 1, "真心": 2, "难过": 2, "离开": 2, "一世": 1, "安宁": 1, "期待": 1, "回忆": 3, "展开": 1, "两个": 2, "动人": 1, "青涩": 2, "温和": 1, "演技": 8, "刻画": 1, "本质": 1, "爱人": 8, "成为": 2, "奢求": 1, "盛名之下": 1, "起初": 1, "以为": 5, "理发": 1, "小哥": 1, "片儿": 1, "科学": 1, "怪人": 1, "园丁": 2, "差一点": 1, "理发师": 1, "知道": 14, "这货儿": 1, "杰克": 1, "妞儿": 1, "媳妇": 1, "重要": 2, "1990": 3, "看来": 2, "肯定": 1, "很多": 4, "受过": 1, "此片": 3, "影响": 2, "比如": 1, "总动员": 1, "remember": 1, "how": 1, "Tim": 6, "Burton": 6, "made": 1, "the": 2, "houses": 1, "in": 2, "neighborhood": 1, "very": 1, "colorful": 1, "and": 2, "similar": 1, "to": 3, "cupcakes": 1, "Cute": 1, "夜里": 1, "TimBurton": 4, "酷爱": 1, "黑暗": 3, "华丽": 1, "内心世界": 3, "炙热": 1, "女孩": 4, "起舞": 2, "满面": 2, ".......": 1, "塑造": 2, "第一个": 2, "善心": 1, "一份": 1, "02": 1, "相见恨晚": 2, "至今": 1, "想起": 2, "depp": 7, "女主送": 1, "满天飞": 1, "情景": 1, "第一次": 1, "认识": 1, "同样": 3, "惊为天人": 1, "像是": 1, "公主": 1, "天使": 3, "雪里": 1, "父亲": 1, "拿出": 1, "辞世": 1, "潸然泪下": 1, "桥段": 1, "昭示": 1, "不可思议": 1, "往往": 2, "易碎品": 1, "苍老": 1, "背后": 1, "飘下": 1, "雕像": 1, "年轻": 3, "不必": 1, "朴实": 1, "欲望": 1, "并非": 1, "别人": 1, "达到": 1, "每件事": 1, "总会": 1, "导火索": 1, "用来": 1, "熄灭": 1, "火心": 1, "恐怕": 1, "教授": 1, "处事": 1, "礼仪": 1, "发明者": 1, "念诗": 1, "人群": 1, "教会": 1, "如何": 2, "成长": 1, "漫天": 2, "思绪": 1, "纷飞": 4, "仅仅": 1, "不想": 1, "错过": 1, "而已": 2, "一句": 3, "评论": 1, "差点": 1, "掉泪": 1, "恰恰": 1, "更该": 1, "一栋": 1, "房子": 4, "Kim": 4, "Edward": 9, "晚上": 2, "月亮": 2, "升起": 2, "光照": 2, "门口": 2, "月光": 2, "女神": 3, "满足": 2, "愿望": 2, "想要": 3, "紧紧": 3, "地拥": 3, "怀中": 3, "哪怕": 5, "JOHNNY": 2, "TIM": 2, "BURTON": 2, "套用": 1, "功夫": 1, "冯小刚": 1, "台词": 1, "他俩": 1, "而加": 1, "一分": 1, "什么": 5, "能够": 1, "赖德": 2, "分开": 1, "除非": 1, "一人": 1, "然而": 1, "事儿": 1, "发生": 1, "好好": 1, "就算": 2, "如此": 5, "虽然": 9, "某些": 1, "疏漏": 1, "内涵": 1, "远远": 2, "大于": 1, "形式美": 1, "接受": 4, "限度": 1, "虽能": 1, "要活": 1, "即便": 2, "伟大": 1, "拯救": 1, "第一部": 2, "那时": 5, "目光": 1, "苍白": 7, "脸颊": 1, "WINONA": 1, "RYDER": 1, "真实": 2, "收场": 1, "蝙蝠侠": 1, "确立": 1, "好莱坞": 1, "地位": 1, "开山": 1, "之作": 2, "树立": 1, "个人": 2, "这是": 4, "现代": 2, "创新": 1, "孩童": 1, "赋予": 1, "本片": 1, "独树一帜": 1, "视觉": 1, "影片": 3, "相当": 2, "惊艳": 3, "記得": 1, "看過": 1, "一本": 1, "關於美國": 1, "近代史": 1, "電影": 2, "影響": 1, "出現": 1, "給予": 1, "評價": 1, "愛德華": 1, "代表": 2, "社會": 1, "一類": 1, "大眾": 1, "甚至": 3, "反感": 1, "內心": 1, "或許": 1, "將電影": 1, "本身": 1, "政治化": 1, "一種": 1, "解讀": 1, "覺得": 1, "這部": 1, "建構": 1, "存在": 1, "人和物": 1, "滿足": 1, "我們": 1, "美女": 2, "野獸": 1, "童話": 1, "情節": 1, "僅此": 1, "特长": 1, "天真": 2, "追求": 3, "原因": 1, "失败": 1, "....": 2, "男人": 2, "究竟": 1, "身怀": 1, "天赋": 1, "异禀": 1, "一个个": 1, "怪诞": 2, "角色": 3, "演绎": 3, "入木三分": 1, "真是": 3, "万分": 1, "敬仰": 1, "自从": 1, "白雪皑皑": 1, "终于": 4, "大家": 1, "年轻貌美": 1, "一塌糊涂": 2, "豆瓣": 1, "8.7": 1, "IMDB": 1, "8.0": 1, "seriously": 1, "要不是": 1, "打死": 1, "看不下去": 1, "温馨": 2, "摆脱": 1, "来说": 2, "仍旧": 1, "哀伤": 1, "资料馆": 1, "展映": 1, "没想到": 3, "银幕": 1, "过火": 1, "夸张": 1, "音乐": 1, "摄影": 1, "根本": 1, "发挥": 1, "演完": 1, "细节": 1, "粗糙": 1, "城堡": 4, "一看": 1, "摄影棚": 1, "照明灯": 1, "看见": 1, "太有": 2, "冰和风": 1, "哪来": 1, "骗骗": 1, "小孩": 1, "适合": 2, "18": 1, "以上": 1, "两星": 1, "女主角": 1, "冰雪": 1, "中一袭": 1, "白裙": 2, "仿佛": 1, "不食": 1, "人间烟火": 1, "梦幻": 1, "色调": 1, "哪里": 2, "那里": 1, "好几年": 1, "色彩斑斓": 1, "超现实": 1, "房屋": 1, "怪异": 2, "令人生厌": 1, "邻居们": 2, "世间": 2, "独特": 1, "超凡": 1, "离真爱过": 1, "人太远": 1, "............": 1, "难以想象": 1, "演得": 2, "魔幻": 1, "二人": 1, "一类": 1, "修剪": 2, "技术": 1, "很赞": 1, "我家": 1, "要是": 1, "哈哈": 1, "小狗": 1, "师奶": 1, "偶像": 1, "女主": 4, "漂亮": 2, "一会": 1, "一下": 2, "中兴": 1, "主题": 1, "影院": 1, "二号": 1, "不错": 1, "好久没": 1, "猫扑": 1, "有位": 1, "烧饼": 1, "肖申克": 1, "部好": 1, "http": 2, "movie": 1, "douban": 1, "com": 2, "subject": 1, "1292370": 1, "discussion": 1, "26598706": 1, "误入": 1, "一群": 1, "肉手": 1, "如刀": 1, "似剑般": 1, "别说": 1, "异类": 1, "不信任感": 1, "那年": 1, "17": 1, "25": 1, "金童玉女": 1, "热烈": 1, "留在": 1, "光影": 1, "灵魂": 1, "家庭": 1, "人生": 1, "迷茫": 1, "学会": 1, "感恩": 1, "遇见": 1, "爱过": 1, "献给": 1, "无助": 2, "丑恶": 2, "其中": 1, "......": 1, "虽是": 1, "似足": 1, "50": 1, "哀怨": 1, "心头": 2, "所爱": 1, "缤纷": 2, "四落": 1, "残枝": 1, "败叶": 1, "炫丽夺": 1, "难道": 1, "只似": 1, "WINO": 1, "FOEVER": 1, "呜呜": 2, "那句": 1, "放下": 1, "起刀": 1, "从来": 1, "品尝": 1, "寒冷": 1, "甜美": 1, "痛苦": 4, "遇到": 1, "从来不": 1, "房间": 1, "各种类型": 1, "游刃有余": 1, "面孔": 2, "表情": 1, "小鹿": 1, "演活": 1, "痴情": 1, "同鞋": 1, "脸症": 1, "烟熏": 1, "刷墙": 1, "漆加": 1, "毁容": 1, "要死": 1, "多人": 1, "后现代": 1, "复杂": 1, "没什么": 3, "立意": 1, "怀疑": 1, "删减": 1, "没话说": 1, "www": 1, "tudou": 1, "programs": 1, "view": 1, "sZmkJaePRjA": 1, "里面": 4, "极了": 1, "Klaus": 1, "Nomi": 1, "不管": 1, "黑色": 3, "嘴唇": 1, "两只手": 1, "摆放": 1, "大腿": 1, "两侧": 1, "流眼泪": 1, "糯米": 1, "我来": 1, "阴沉": 1, "犹豫": 1, "雨滴": 1, "浑浊": 1, "河流": 1, "疾走": 1, "逃避": 1, "远处": 1, "情侣": 1, "分手": 2, "序幕": 1, "顾城": 1, "初春": 1, "一年": 2, "爱情片": 2, "科幻": 1, "成分": 1, "工业": 1, "时代": 1, "人类文明": 1, "碰撞": 1, "那场": 1, "雪太": 1, "不了": 2, "片中": 1, "提到": 1, "换手": 2, "冗余": 1, "听说": 1, "某国": 1, "老师": 1, "学生": 1, "灰姑娘": 1, "漏洞": 1, "水晶鞋": 1, "消失": 1, "毁成": 1, "很帅": 1, "难怪": 1, "小金人": 1, "下次": 1, "直接": 2, "硫酸": 1, "算了": 1, "科幻片": 2, "中竟": 1, "凄美": 2, "带给": 1, "意想不到": 1, "凄楚": 1, "记住": 2, "反差": 1, "太大": 1, "日臻成熟": 1, "两位": 1, "主演": 3, "定情": 1, "可惜": 4, "劳燕分飞": 1, "事物": 1, "多半": 1, "停留": 1, "太久": 1, "道理": 2, "太小": 1, "高中生": 1, "亮点": 1, "造出来": 1, "局促不安": 1, "纠结": 1, "散发": 1, "爱着": 1, "梦想": 1, "犀利": 1, "雕刻": 1, "爱恋": 1, "整个": 2, "冬天": 2, "心动": 1, "怎能不": 1, "孤僻": 2, "美少女": 1, "没法": 2, "实在": 2, "太美": 1, "果然": 4, "不合": 1, "常理": 1, "突兀": 1, "交代": 1, "清楚": 1, "整体": 1, "bgm": 1, "好赞": 1, "edward": 1, "简直": 2, "小天使": 1, "winona": 2, "ryder": 1, "超级": 1, "确实": 1, "太爱": 1, "美国": 2, "电影吧": 1, "美的": 1, "表达": 2, "ps": 1, "那些": 5, "纯色": 1, "喜剧片": 1, "老妈": 1, "共谱": 1, "姐弟恋": 1, "神马": 1, "雪雕": 1, "富含": 1, "充分": 1, "情感": 2, "当然": 1, "离不开": 1, "深沉": 1, "包围": 1, "爱将": 1, "Deep": 1, "青春": 1, "貌美": 1, "Ryder": 3, "悲凉": 1, "助人为乐": 1, "权利": 1, "躲起来": 1, "可是": 5, "一连串": 1, "意外": 1, "事情": 1, "周围": 1, "态度": 1, "变成": 2, "好心": 1, "坏事": 2, "高清": 1, "一边": 3, "聊天": 1, "结果": 1, "泪流满面": 2, "这些": 1, "长进": 1, "Winona": 7, "真美": 1, "太好了": 1, "好汉": 1, "Berta": 1, "哎哟": 1, "典型": 1, "一步步": 1, "误会": 1, "走到": 1, "孤立": 1, "公敌": 1, "再见": 1, "恶意": 1, "一切": 2, "承担": 1, "这太": 1, "公平": 1, "悔恨": 1, "度过": 1, "这才": 1, "意义": 1, "多少": 2, "还会": 1, "流泪": 2, "回想": 1, "飞舞": 1, "身穿": 1, "旋转": 1, "美若天仙": 1, "若娜": 1, "一袭": 1, "白衣": 1, "长裙": 1, "制造": 1, "陶醉": 1, "舞动": 1, "心目": 1, "荧幕": 1, "瞬间": 1, "之一": 1, "怨念": 1, "怎么": 2, "多配": 1, "两人": 1, "六七年": 1, "剪树": 1, "剪毛": 1, "全都": 1, "忘光": 1, "更是": 1, "忘得": 1, "彻底": 1, "重看": 1, "十分": 1, "设定": 1, "融入": 1, "却会": 1, "带来": 1, "冰是": 1, "男孩": 1, "脸上": 1, "笑容": 1, "小心翼翼": 1, "激发": 1, "思春": 1, "之情": 1, "应该": 1, "johnny": 2, "盛名难副": 1, "构思": 1, "巧妙": 1, "离奇": 1, "始终": 2, "欠缺": 1, "力道": 1, "毕竟": 2, "当做": 1, "信仰": 1, "终究": 2, "逃不过": 1, "命运": 1, "洗去": 1, "forever": 1, "纹身": 2, "是否": 2, "腌制": 1, "起来": 1, "送给": 1, "孩子": 2, "生儿育女": 1, "白头到老": 1, "Why": 1, "you": 4, "do": 2, "it": 1, "Because": 2, "asked": 2, "绝对": 1, "演技派": 1, "自然": 1, "完后": 1, "想想": 1, "不能自己": 1, "完真": 1, "虐心": 1, "周星驰": 1, "恶搞": 1, "然后": 1, "以后": 2, "讨厌": 1, "下雪天": 1, "是因为": 1, "合作": 1, "怪胎": 1, "阻止": 1, "精诚所至": 1, "金石为开": 1, "原谅": 1, "盲症": 1, "病入膏肓": 1, "不知": 2, "猪脚": 1, "加勒比海": 1, "tim": 1, "burton": 1, "组合": 1, "不厌": 1, "奋不顾身": 1, "小男孩": 1, "急切": 1, "担心": 1, "受伤": 1, "却不曾": 1, "此刻": 1, "窗前": 1, "阴森": 1, "印证": 1, "一点儿": 1, "停下来": 1, "又名": 1, "上映": 1, "年度": 1, "语言": 1, "英语": 1, "制片": 1, "国家": 1, "地区": 1, "imdb": 1, "链接": 1, "tt0099487": 1, "年复一年": 2, "地住": 1, "想着": 1, "如常": 1, "结婚": 1, "生子": 1, "一如": 1, "是从": 1, "这位": 1, "奇才": 1, "名字": 1, "淋漓": 1, "精致": 1, "敏感": 1, "妖娆": 1, "彷如": 1, "量身": 1, "定制": 1, "惊恐": 3, "成就": 1, "五星": 1, "鹅毛": 1, "天儿": 1, "念想": 1, "尖锐": 1, "一颗": 2, "无缘无故": 1, "相见": 1, "那一刻": 1, "深爱": 2, "大爱": 2, "johnnydepp": 1, "双眼": 1, "给予": 1, "将近": 1, "大学": 1, "时光": 1, "每每": 1, "Howard": 1, "No": 1, "昨天": 1, "TAT": 1, "充斥": 1, "五颜六色": 2, "单调": 1, "黑白": 1, "初生儿": 1, "面对": 1, "恐怖": 2, "向往": 2, "一定": 3, "长相": 1, "厮守": 1, "只要": 2, "何尝不可": 1, "很喜": 1, "天马": 1, "星空": 1, "牺牲": 1, "色相": 1, "女主脚": 1, "人人": 2, "难以": 1, "见容": 1, "为了": 1, "保有": 1, "这份": 1, "鸡犬相闻": 1, "老死不相往来": 1, "2010.3": 1, "14": 1, "距离": 1, "It": 1, "could": 1, "be": 1, "better": 1, "之所以": 1, "人设": 1, "全部": 1, "如冰般": 1, "纯洁": 1, "Social": 1, "PSY": 1, "film": 1, "上课": 1, "苛求": 1, "当人": 1, "Ostracism": 1, "强大": 1, "力量": 2, "在于": 1, "造成": 1, "心理": 1, "上去": 1, "肉体": 1, "分割": 1, "一如既往": 1, "没有勇气": 1, "special": 1, "第一遍": 1, "听闻": 1, "虔诚": 1, "心去": 1, "点点": 1, "友善": 1, "超越": 1, "对不起": 1, "办法": 1, "欣赏": 1, "光是": 1, "一张": 1, "而面": 1, "无表情": 1, "说不出口": 1, "委屈": 1, "兑现": 1, "独自一人": 1, "众人": 1, "骂声": 1, "回到": 1, "糖果": 1, "丢失": 1, "一齐": 1, "唏嘘": 2, "可怜": 1, "心爱": 2, "女人": 1, "心是": 1, "强尼戴": 1, "普在": 1, "社会": 2, "要么": 2, "毁灭": 1, "鲜艳": 2, "强烈": 1, "鲜明": 1, "对比": 1, "非凡": 1, "创造力": 1, "遗落": 1, "大片": 1, "绿地": 1, "屋子": 1, "轿车": 1, "穿着": 1, "亮丽": 1, "色彩": 3, "树木": 1, "锦上添花": 1, "抹黑": 1, "纯白": 1, "融合": 1, "进去": 1, "怪不得": 2, "认出": 1, "kim": 2, "黑天鹅": 1, "beth": 1, "同一个": 1, "21": 1, "沧桑": 1, "love": 1, "热泪盈眶": 1, "看起来": 1, "怪怪": 1, "很能": 1, "leon": 1, "再次": 1, "真素": 1, "娇羞": 1, "怯生生": 1, "雅芳": 1, "母爱": 1, "泛滥": 1, "冷组": 1, "打起": 1, "飞机": 1, "围着": 1, "飘舞": 1, "最美": 1, "懵懂": 1, "何物": 1, "一阵": 1, "失落": 1, "伤疤": 1, "下去": 1, "纯净": 1, "好久": 1, "稀里哗啦": 1, "说实话": 1, "出现": 1, "隐隐": 1, "吓了一跳": 1, "泪如泉涌": 1, "崩溃": 1, "好片": 1, "弄伤": 1, "不是故意": 1, "CCAV6": 1, "DEEP": 1, "小丫头": 1, "中透": 1, "抵挡": 1, "勇士": 1, "历尽": 1, "艰难险阻": 1, "战胜": 1, "恶龙": 2, "抢回": 1, "宝石": 3, "迎接": 1, "鲜花": 1, "掌声": 1, "更想": 1, "丑陋": 1, "掌心": 1, "心地善良": 1, "无穷": 1, "分毫": 1, "雨天": 1, "依靠": 1, "王子": 1, "man": 1, "specialized": 1, "solitary": 1, "不靠": 1, "黑木耳": 1, "眼里": 1, "美术": 1, "大师": 1, "怀里": 1, "开端": 1, "悲壮": 1, "我留": 1, "舍不得": 1, "剪下": 1, "一片片": 1, "地够": 1, "驾驭": 1, "8.4": 1, "片段": 1, "为数不多": 1, "愿意": 1, "违背": 1, "客观": 1, "奇幻": 1, "车子": 1, "手上": 1, "皮肤": 1, "紧握": 1, "尽管": 1, "那双": 1, "特殊": 1, "手下": 1, "创造": 1}