{"每次": 3, "这些": 4, "神作": 2, "时候": 19, "想到": 2, "这是": 9, "动画片": 12, "一群": 2, "一笔": 1, "笔画": 1, "出来": 3, "觉得": 21, "漏看": 1, "一帧": 2, "实在": 2, "对不起": 1, "他们": 4, "努力": 12, "工作": 6, "变成": 16, "发生": 5, "可能": 11, "忘记": 22, "只不过": 2, "想不起": 2, "罢了": 4, "十年": 1, "后重": 1, "大哭": 1, "其实": 5, "我们": 23, "明白": 2, "这个": 12, "结局": 3, "认为": 3, "宫崎骏": 76, "最好": 13, "一部": 25, "恐怖片": 1, "有些": 12, "事情": 7, "只是": 8, "一时": 5, "想不起来": 5, "怎么": 2, "打动": 3, "好像": 9, "不是": 13, "而是": 4, "震撼": 2, "贪吃": 7, "那么": 10, "经典": 12, "还是": 12, "成人": 3, "动画": 27, "估计": 1, "大部分": 1, "中国": 1, "观众": 2, "很难": 4, "体会": 3, "什么": 8, "内个": 1, "白龙": 8, "塔矢亮": 1, "爱丽丝": 3, "漫游": 1, "奇遇记": 1, "东方": 2, "一点": 1, "模糊": 1, "爱情": 5, "...": 3, "小白龙": 3, "报恩": 1, "千寻": 38, "想起": 2, "自己": 20, "情人": 1, "名字": 16, "客人": 2, "洗澡": 1, "煤球": 2, "来回": 1, "经历": 2, "好玩儿": 1, "一定": 10, "不会": 5, "大猪": 1, "不乱": 1, "东西": 5, "干干净净": 1, "永远": 7, "回到": 1, "14": 1, "往下": 1, "眼泪": 1, "上流": 1, "一条": 3, "河流": 1, "琥珀": 4, "不能": 17, "因为": 4, "一切": 4, "曾经": 6, "相遇": 1, "沉浸": 1, "怀抱": 1, "小时候": 5, "多想": 1, "一个": 22, "一样": 8, "男朋友": 1, "寻找": 3, "自我": 4, "或者": 2, "复苏": 1, "过程": 4, "认可": 1, "片儿": 1, "考试": 1, "别人": 2, "复习": 2, "专业课": 1, "人间": 2, "渣滓": 1, "这种": 6, "世界": 18, "沉迷": 1, "真是": 3, "现实": 8, "消极": 1, "逃避": 1, "真的": 25, "碰到": 1, "这样": 4, "天呐": 1, "绝对": 2, "豆瓣": 1, "干嘛": 1, "电影": 28, "即使": 6, "短暂": 1, "一瞥": 1, "莫大": 1, "力量": 1, "就是": 16, "想要": 1, "激动": 1, "幸福": 5, "这部": 12, "激发": 1, "日本": 14, "兴趣": 1, "预言": 1, "难以": 2, "表述": 1, "感受": 4, "怪诞": 1, "温暖": 9, "治愈": 5, "总之": 1, "这辈子": 1, "看过": 17, "为什么": 5, "现在": 6, "欲望": 5, "无限": 2, "失去": 1, "进而": 1, "痛失": 1, "残酷": 1, "环境": 3, "只有": 5, "适应": 1, "寻求": 1, "改变": 1, "才能": 3, "突破": 1, "成功": 4, "伯乐": 1, "重要": 4, "记得": 7, "感恩": 2, "奋斗": 2, "途中": 1, "妖魔鬼怪": 1, "可爱": 4, "无脸": 24, "小白": 2, "节制": 1, "不断": 1, "进阶": 1, "世故": 3, "做个": 1, "善良": 10, "温度": 1, "吃掉": 1, "很多遍": 3, "印象": 11, "最深": 6, "爸爸妈妈": 5, "拼命": 1, "小女孩": 3, "大喊": 2, "一声": 1, "还有": 12, "漂亮": 2, "男主角": 2, "房子": 1, "当地": 1, "建筑": 1, "作为": 1, "宣传点": 1, "人人": 1, "否则": 2, "生活": 4, "第一次": 5, "年龄": 2, "起来": 5, "有点": 4, "惭愧": 1, "家里人": 1, "比较": 1, "高考": 1, "毕业": 1, "作品": 21, "一遍": 6, "但是": 6, "千与千寻": 14, "很小": 1, "接触": 3, "不过": 3, "了解": 2, "不够": 1, "深刻": 10, "里面": 7, "很多": 18, "画面": 14, "不可思议": 3, "比如": 2, "人变": 1, "类似": 1, "有种": 1, "贴心": 1, "感觉": 7, "好看": 20, "没有": 10, "迪斯尼": 1, "花哨": 1, "甚至": 2, "落伍": 1, "直到现在": 1, "坚持": 3, "手工": 1, "绘画": 1, "电脑": 1, "绘图": 1, "完成": 1, "卡通片": 2, "懂得": 2, "影片": 8, "应该": 4, "所以": 3, "笔下": 1, "形象": 2, "个人": 3, "一个个": 1, "知觉": 1, "卡通": 1, "内心": 6, "天马行空": 6, "想象力": 8, "配以": 1, "精致": 2, "大气": 2, "令人窒息": 1, "安静": 1, "精益求精": 1, "浮躁": 1, "灵魂": 2, "出此": 1, "杰作": 1, "隐喻": 7, "充满": 14, "童真": 3, "令人感动": 1, "同时": 3, "忧伤": 1, "值得": 6, "回味": 3, "不仅": 2, "揭露": 2, "人性": 9, "贪婪": 15, "同样": 2, "充斥": 1, "满满的": 2, "温情": 3, "虚伪": 1, "欺骗": 1, "奸诈": 1, "陪伴": 2, "照顾": 1, "告诉": 4, "不管": 9, "前方": 5, "艰难": 1, "注定": 1, "离开": 2, "人生": 6, "接下来": 1, "好比": 1, "事是": 1, "不敢": 2, "回忆": 6, "然后": 3, "久而久之": 1, "遗忘": 1, "代表": 1, "记忆": 3, "之门": 1, "某些": 1, "事物": 1, "触发": 1, "心头": 1, "另外": 1, "台词": 3, "不要": 11, "吃太多": 3, "太多会": 1, "杀掉": 7, "在生活中": 1, "或许": 3, "每个": 5, "过千寻": 1, "父母": 9, "那样": 1, "遇到": 3, "唾手可得": 1, "便宜": 1, "总是": 5, "无法": 3, "抑制": 1, "从不": 1, "考虑": 1, "后果": 1, "最终": 3, "为此": 1, "付出": 2, "沉重": 1, "代价": 2, "所有人": 3, "能够": 2, "误入": 1, "迷踪": 1, "时得": 1, "遇白龙": 1, "所有": 4, "长辈": 2, "一如": 1, "锅炉": 1, "爷爷": 2, "夜里": 1, "棉被": 1, "嘴硬": 1, "心软": 1, "汤屋": 3, "回归": 4, "脸人": 2, "变化": 1, "可逆": 1, "回头": 9, "一生": 2, "许多路": 2, "成长": 8, "不能自己": 2, "掌控": 2, "孤单": 2, "寂寞": 2, "继续": 2, "下去": 2, "不许": 2, "很久以前": 2, "重温": 5, "一次": 3, "感触": 2, "更深": 1, "当千寻": 1, "太胖": 7, "这么": 3, "道理": 2, "简单明了": 1, "表达出来": 1, "看到": 3, "人心": 5, "特别": 7, "动漫": 28, "老师": 2, "喜欢": 57, "对千寻": 2, "感情": 2, "纯粹": 1, "天空": 2, "龙猫": 2, "讲述": 2, "人与自然": 1, "关系": 2, "最后": 3, "只会害": 1, "有千寻": 1, "纯真": 4, "感动": 9, "拍成": 1, "时隔多年": 1, "婆婆": 5, "人手": 1, "已经": 4, "无能": 1, "胆小鬼": 1, "的话": 2, "最脏": 1, "最累": 1, "活派": 1, "phd": 1, "申请": 1, "多么": 5, "逐渐": 1, "过去": 1, "选择": 1, "留下": 4, "长大": 2, "初中": 1, "动画电影": 9, "奇幻": 2, "旅程": 1, "充满活力": 1, "想象": 2, "原来": 1, "小孩子": 4, "感人": 6, "就是说": 1, "丑恶": 2, "希望": 5, "温情脉脉": 1, "列车": 3, "美好": 6, "体现": 1, "最近": 1, "一直": 9, "白龙会": 1, "再次": 2, "重逢": 1, "大爱无脸": 1, "多苦": 4, "只要": 5, "方向": 4, "正确": 5, "崎岖不平": 4, "原地": 4, "接近": 4, "期待": 2, "我国": 1, "一天": 3, "水平": 1, "看部": 1, "回过头来": 1, "反而": 1, "对无脸": 1, "剧情": 9, "一家人": 1, "来到": 2, "废弃": 1, "游乐场": 4, "探险": 1, "爸妈": 3, "食物": 2, "独自一人": 1, "生存": 4, "故事": 20, "具备": 1, "许多": 2, "优点": 1, "坚强": 4, "勇敢": 10, "放弃": 1, "精神": 2, "得到": 1, "帮助": 2, "凭借": 1, "勤奋": 3, "解救": 1, "温馨": 3, "朴实": 2, "老少皆宜": 2, "合家欢": 1, "有趣": 3, "略显": 1, "平淡": 2, "整体": 2, "一般": 2, "东方人": 1, "意义": 2, "真是太": 1, "关于": 1, "第一部": 3, "高中": 1, "放荡不羁": 1, "美术": 1, "课上": 1, "开始": 9, "人物形象": 1, "不清": 2, "当时": 2, "人住": 1, "宿舍": 1, "晚上": 1, "睡觉": 1, "害怕": 3, "哈哈": 2, "不错": 7, "深思": 2, "由于": 1, "其他": 2, "多次": 1, "最高峰": 1, "之一": 5, "后辈": 1, "叹为观止": 1, "做人": 3, "做事": 1, "准则": 1, "有用": 1, "未必": 1, "如此": 3, "需要": 2, "用心": 1, "独立": 1, "思考": 3, "能力": 1, "非常": 13, "超级": 1, "发现": 4, "很棒": 2, "每部": 3, "好几遍": 2, "可以": 10, "百看不厌": 2, "日式": 1, "好莱坞": 1, "无论": 7, "立意": 1, "角度": 2, "截然不同": 1, "污染": 1, "以及": 4, "深度": 1, "系列": 2, "丢掉": 1, "以前": 3, "深入": 1, "人生哲理": 2, "看似": 2, "懵懂": 1, "无知": 1, "孩童": 1, "往往": 2, "最先": 1, "预知": 1, "危险": 1, "诱惑": 2, "面前": 2, "更加": 1, "坚定": 1, "那些": 4, "历经": 2, "世间": 1, "百态": 1, "大人": 5, "容易": 2, "眼前": 1, "假象": 1, "迷惑": 1, "一再": 1, "妥协": 1, "坚守": 1, "原则": 1, "可悲": 1, "大多": 1, "自知": 1, "太有": 1, "前途": 1, "一贯": 1, "风格": 2, "自然": 1, "真善美": 2, "年少时": 1, "一辈子": 1, "征服": 1, "全世界": 1, "不仅仅": 1, "老爷子": 2, "高超": 1, "创作": 1, "执导": 2, "吉卜力": 5, "精湛": 1, "制作": 4, "主题": 1, "内核": 1, "寓意深长": 1, "民间": 1, "神话": 2, "传说": 1, "整部": 2, "魔力": 1, "一度": 1, "这幅": 1, "样子": 1, "截图": 1, "get": 1, "不到": 2, "孩子": 9, "注意": 1, "惩罚": 1, "知道": 9, "克制": 1, "暴饮暴食": 1, "有意思": 2, "独特": 1, "新奇": 2, "值得一看": 2, "超赞": 1, "梦幻": 1, "见到": 1, "哪次": 1, "不经意": 1, "再见": 2, "之后": 5, "以后": 5, "久久": 1, "循环": 1, "播放": 1, "片尾曲": 1, "几天": 2, "前段时间": 1, "没看": 1, "无聊": 3, "一下": 1, "解药": 1, "千寻刚": 1, "后来": 4, "慈祥": 1, "锅炉房": 1, "齐心协力": 1, "河神": 1, "清除": 1, "污垢": 1, "一段": 1, "加入": 1, "环保": 2, "概念": 1, "溺爱": 2, "折射": 1, "一些": 2, "看法": 1, "地方": 3, "佳作": 2, "面对": 1, "未知": 1, "背景音乐": 2, "配乐": 5, "老先生": 2, "不间断": 1, "几次": 2, "配音": 1, "好听": 2, "听说": 1, "内容": 2, "含义": 1, "很大": 1, "几刷": 1, "何时": 3, "回家": 1, "无稽之谈": 1, "幻想": 1, "进入": 1, "替人": 1, "一场": 2, "白日": 1, "童梦": 1, "莫名": 2, "守护": 2, "持续": 1, "相随": 1, "小少爷": 1, "义气": 1, "相助": 1, "一路": 1, "幸运": 1, "道别": 2, "幸好": 1, "信念": 1, "追随": 1, "无可挽回": 1, "倒不如": 1, "一梦": 1, "方休": 1, "武器": 1, "超能力": 1, "打斗": 1, "冒险": 1, "描述": 1, "正义": 1, "邪恶": 1, "斗争": 1, "善恶": 1, "交错": 1, "社会": 4, "如何": 1, "跟随": 1, "磨难": 1, "一起": 5, "拾起": 1, "真诚": 5, "好好": 2, "做鬼": 1, "同一个": 1, "目的": 1, "不惜一切": 1, "心甘情愿": 1, "成为": 3, "金钱": 2, "奴隶": 1, "死心塌地": 1, "一趟": 1, "开往": 2, "坟墓": 2, "中途": 1, "下车": 1, "不太懂": 1, "完全": 2, "伤痛": 1, "最爱": 4, "角色": 2, "也好": 1, "每年": 1, "算是": 1, "满足": 2, "带来": 1, "灾难": 1, "某个": 1, "年龄段": 1, "终于": 3, "超过": 1, "幽灵公主": 1, "心中": 2, "No1": 1, "好多": 3, "纠结": 1, "男孩": 1, "妹妹": 1, "纯洁": 1, "明亮": 2, "眼神": 1, "那条": 1, "天才": 1, "厉害": 2, "次数": 1, "最多": 1, "初一": 1, "多少": 3, "这次": 2, "旅途": 1, "最爱无脸": 1, "铭记": 1, "挺不错": 1, "跟风": 1, "连续": 1, "好几部": 1, "质感": 1, "BGM": 1, "情节": 3, "是非": 1, "黑白": 1, "界定": 1, "正如": 1, "坏人": 2, "背后": 1, "辛酸": 1, "一面": 1, "为了": 1, "救回": 3, "懦弱": 1, "慵懒": 1, "普通": 2, "蜕变": 1, "少女": 3, "干净": 1, "唯美": 3, "适合": 2, "反思": 1, "踏上": 1, "之路": 1, "开端": 1, "细腻": 1, "画风": 3, "走心": 1, "思想": 1, "浅显": 1, "表达": 1, "足够": 1, "爱上": 1, "并且": 2, "几乎": 1, "失望": 1, "属于": 3, "这里": 3, "日语": 1, "发音": 1, "影响": 4, "迷失": 3, "忘掉": 1, "何况": 1, "童年": 2, "台湾": 1, "九份": 2, "石阶": 1, "路上": 1, "忽生": 1, "戚戚": 1, "之感": 1, "场景": 1, "结果": 1, "原型": 1, "无以": 1, "言表": 1, "兴奋": 1, "惊喜": 1, "回来": 2, "重看": 2, "怀念": 1, "雨蒙蒙": 1, "老松": 1, "榻榻米": 1, "喜爱": 1, "偶像": 1, "粉丝": 1, "显示": 1, "人类": 1, "地道": 1, "二维": 1, "很少": 1, "执着": 4, "缺少": 1, "哪里": 5, "漂移": 1, "镜头": 1, "质朴": 2, "浓缩": 1, "荒诞": 1, "华丽": 1, "人们": 4, "审视": 1, "察觉": 1, "指引": 1, "净化": 1, "心灵": 2, "坚实": 1, "短评": 1, "Tas": 1, "一句": 3, "不然": 3, "动画人物": 1, "受欢迎": 1, "就值": 1, "还会": 1, "那里": 1, "相逢": 1, "消失": 1, "再也": 1, "回不去": 1, "不见": 1, "唯一": 1, "橡皮筋": 1, "大步": 2, "往前走": 1, "2013": 1, "居然": 1, "感悟": 1, "当年": 2, "不同": 4, "警世": 1, "经典影片": 1, "童趣": 2, "富含": 2, "漫画": 1, "尤其": 1, "记住": 1, "颇深": 1, "如果": 2, "经典作品": 1, "佩服": 1, "哎呀": 1, "一种": 1, "说不出来": 1, "梦游": 1, "仙境": 1, "细节": 3, "似乎": 2, "深究": 2, "爱恨": 1, "情仇": 1, "举重若轻": 1, "东方式": 1, "禅意": 1, "竟然": 1, "白和千寻": 2, "清水": 1, "飞翔": 1, "蓝天": 1, "少年": 1, "不灭": 1, "梦想": 1, "青涩": 1, "若永葆": 1, "这份": 3, "心动": 1, "走过": 1, "长长的": 1, "神奇": 2, "神明": 1, "梦境": 1, "呼唤": 1, "命运": 1, "联结": 1, "符咒": 1, "获得": 1, "契机": 1, "多年": 2, "后无脸": 1, "孤寂": 1, "最是": 1, "动人": 1, "只想": 1, "静静": 1, "穿过": 1, "这片海": 1, "富有": 2, "寓言": 1, "人生哲学": 1, "老爷爷": 2, "年轻": 1, "保守": 1, "立场": 1, "止步": 1, "不知": 5, "原因": 2, "变得": 1, "展现": 2, "天性": 1, "好奇": 1, "魔幻": 1, "味道": 1, "十足": 1, "故事情节": 1, "各种各样": 1, "五星": 1, "力荐": 1, "好棒": 1, "高速": 1, "太多要": 1, "个度": 1, "遭报应": 1, "淘汰": 1, "直入": 1, "不像": 1, "一针见血": 1, "慢慢": 1, "要说": 1, "更好": 1, "巨作": 1, "虽然": 3, "效果": 1, "不论": 1, "他俩": 1, "朋友": 2, "在乎": 1, "一段时间": 1, "变坏": 1, "想着": 1, "片段": 1, "姐姐": 1, "那个": 6, "耗子": 1, "撒娇": 1, "耍赖": 1, "必须": 1, "担当": 1, "只能": 2, "地朝前": 1, "救出": 1, "打造": 1, "完美": 2, "瑰丽": 1, "奇异": 2, "清新": 1, "除了": 1, "主角": 1, "配角": 1, "如数家珍": 1, "剩下": 2, "能量": 1, "片子": 2, "保护": 1, "自然环境": 1, "别太": 1, "天上": 1, "馅饼": 2, "工作室": 1, "未来": 1, "优美": 1, "推荐": 2, "戏剧性": 1, "童话": 2, "奇怪": 1, "小镇": 2, "香喷喷": 1, "千辛万苦": 1, "找回": 1, "耐人寻味": 1, "影评": 2, "联想": 1, "时间": 1, "看一遍": 3, "老宫": 2, "巅峰": 1, "无论是": 1, "达到": 1, "极致": 2, "情绪": 1, "崩溃": 1, "本剧": 1, "一家": 1, "加上": 2, "而且": 4, "大家": 1, "无数遍": 1, "相见": 1, "玄妙": 1, "经典之作": 4, "不下": 1, "十遍": 1, "触动": 3, "会变": 1, "柔软": 2, "日漫": 1, "最初": 1, "放到": 1, "依然": 1, "起伏": 1, "情感": 2, "一流": 1, "意犹未尽": 1, "好美": 1, "特色": 1, "劳动": 1, "变猪": 1, "一次次": 1, "看出": 1, "寓意": 1, "励志": 1, "小孩": 1, "教会": 1, "好吃懒做": 1, "变会成": 1, "一列": 1, "路途": 1, "上会": 1, "有人": 1, "至始": 1, "至终": 1, "下车时": 1, "不舍": 1, "心存": 1, "感激": 1, "挥手": 1, "很暖心": 1, "果然": 2, "同班同学": 1, "心里": 1, "不想": 1, "无面": 1, "出场": 1, "对于": 2, "推动": 1, "作用": 1, "孤独感": 1, "单一": 1, "个体": 1, "发出": 1, "来源于": 1, "冷漠": 1, "带进": 1, "新世界": 1, "哲理": 2, "数最多": 1, "是因为": 1, "经久不衰": 1, "魅力": 1, "献给": 1, "简单": 3, "抽象": 1, "其千寻": 1, "身上": 1, "饱含": 1, "不乏": 1, "光芒": 1, "情亲": 1, "朦胧": 1, "友谊": 1, "之爱": 1, "给予": 1, "真挚": 1, "营造": 1, "光影": 1, "之梦是": 1, "卓尔": 1, "不凡": 1, "令人": 2, "找到": 1, "并肩": 1, "造梦师": 1, "环保主义者": 1, "一半": 2, "长度": 1, "用尽": 1, "法宝": 1, "兔子": 1, "前半段": 1, "节奏": 1, "冲突": 1, "安排": 1, "正常": 1, "前提": 1, "后半段": 1, "胜利": 1, "过于": 1, "顺利": 1, "恐怕": 1, "精彩": 1, "美工": 1, "分镜": 1, "弥补": 1, "缺憾": 1, "评分": 1, "7.6": 1, "必看": 1, "之作": 1, "几年": 1, "火车": 2, "那段": 1, "彻底": 1, "灌醉": 1, "好怀念": 1, "小千对": 1, "友情": 1, "突然": 1, "我覺": 1, "這片": 2, "豐富": 1, "幾年": 1, "承認": 1, "其實": 1, "一個": 1, "大戲": 1, "硬要": 1, "生命": 1, "整個": 1, "企圖": 1, "操作": 1, "有點": 1, "牽強": 1, "怎辦": 1, "只好": 1, "加花樣": 1, "畫畫": 1, "怕畫": 1, "不好": 1, "筆或": 1, "東西": 1, "客不請": 1, "酒席": 1, "沒誠意": 1, "龍貓": 1, "魔女": 1, "宅急": 1, "便皆勝": 1, "本片": 1, "歧視豬": 1, "哈哈哈": 1, "嘆息": 1, "题材": 1, "到底": 1, "透明": 1, "海水": 1, "缓缓": 1, "前行": 1, "风情": 1, "精美": 1, "一如既往": 1, "男好": 1, "温柔": 1, "两次": 1, "小姑娘": 1, "世纪": 1, "经济": 1, "泡沫": 1, "陷入": 1, "疯狂": 1, "暴露": 1, "本部": 1, "毫不": 1, "回避": 1, "各种": 1, "闹剧": 1, "形式": 1, "表现": 1, "反省": 1, "讳言": 1, "态度": 1, "像是": 2, "晚辈": 1, "谆谆教导": 1, "激励": 1, "即将": 1, "直面": 1, "徘徊": 1, "何去": 1, "年青": 1, "两个": 1, "国产": 1, "变回来": 1, "没事": 1, "却说": 1, "搬家": 1, "公司": 1, "就要": 1, "优秀": 2, "澎湃": 1, "渗透": 2, "入心": 1, "恐惧": 1, "酣畅淋漓": 1, "多人": 1, "入画": 1, "心底": 1, "自觉": 2, "几遍": 1, "世界观": 1, "构建": 1, "不明": 1, "元素": 1, "之间": 1, "合乎逻辑": 1, "连接": 1, "巧妙": 1, "对应": 1, "在我看来": 1, "乏善可陈": 1, "纯情": 1, "洗浴城": 1, "观光": 1, "历险记": 1, "算不上": 1, "暂时": 1, "而已": 1, "之前": 1, "十来遍": 1, "说实话": 1, "越发": 1, "田园": 1, "大自然": 1, "这剧": 1, "最大": 1, "那阵": 1, "切除": 1, "霉运": 1, "网上": 1, "剖析": 1, "包含": 3, "杰出": 1, "丰富": 2, "开头": 1, "发展": 1, "大手笔": 1, "结尾": 1, "缺乏": 1, "高潮": 1, "虎头蛇尾": 1, "程度": 1, "观感": 1, "即便如此": 1, "确实": 1, "角落": 1, "历程": 1, "青少年": 1, "观看": 1, "无言": 1, "方式": 1, "甚少": 1, "挺赞": 1, "时间段": 1, "结合": 1, "问题": 1, "视觉": 1, "音乐": 1, "享受": 1, "无尽": 1, "好人": 1, "说不出": 1, "快乐": 1, "伤感": 1, "人物": 2, "因觉": 1, "其脏": 1, "分神": 1, "部分": 1, "可是": 1, "组合": 1, "大概": 1, "愿意": 1, "正面": 1, "色彩": 1, "最为": 1, "斑斓": 1, "意韵": 1, "就象": 1, "万花筒": 1, "着迷": 1, "提到": 1, "首先": 1, "白胡子": 1, "老头儿": 1, "一朵": 1, "小萝莉": 1, "诡异": 1, "叙述": 1, "信以为真": 1, "抽身": 1, "远离": 1, "纷扰": 1, "陆离": 2, "一块": 1, "栖息地": 1, "更为重要": 1, "那句": 1, "无数": 1, "女孩": 1, "毕生": 1, "座右铭": 1, "完整": 1, "没什么": 1, "幼稚": 1, "争取": 1, "抛下些": 1, "乱七八糟": 1, "名气": 1, "强大": 1, "执行力": 1, "脑中": 1, "神鬼": 2, "银幕": 1, "单纯": 1, "姑娘": 1, "轻易": 1, "珍贵": 1, "突兀": 2, "结束": 1, "好似": 1, "跟千寻": 1, "久石": 1, "自成": 1}