{"语言": 3, "匮乏": 1, "搬个": 1, "板凳": 1, "电影院": 11, "门口": 1, "行人": 1, "整座": 1, "岛上": 1, "丁满": 4, "艺名": 1, "出道时": 1, "自身": 2, "面部": 1, "表情": 1, "业内": 1, "看好": 2, "一直": 5, "无名": 1, "早期": 1, "作品": 7, "大宅门": 1, "国度": 1, "94": 1, "参演": 1, "狮子王": 1, "名声大噪": 1, "发行": 1, "单曲": 1, "库拉": 1, "马塔塔": 1, "出演": 1, "电视剧": 1, "彭丁满": 1, "历险记": 1, "全球": 3, "热播": 1, "近期": 1, "少年": 18, "奇幻": 18, "漂流": 12, "有着": 2, "出色": 2, "表演": 2, "观众": 9, "熟知": 1, "心里": 5, "猛虎": 5, "蔷薇": 3, "审视": 3, "心灵": 7, "亲爱": 2, "朋友": 3, "战栗": 2, "因为": 12, "那里": 2, "本来": 3, "面目": 2, "西格": 1, "夫里": 1, "萨松": 1, "父母": 2, "兄弟": 2, "理查": 1, "帕克": 6, "最後都": 2, "頭來": 2, "相信": 33, "人生": 16, "就是": 38, "不斷": 2, "放下": 10, "然而": 4, "痛心": 6, "沒能": 3, "好好": 13, "他們": 2, "All": 2, "of": 4, "life": 2, "is": 5, "an": 2, "act": 2, "letting": 2, "go": 2, "but": 2, "what": 2, "hurts": 2, "the": 3, "most": 2, "not": 2, "taking": 2, "moment": 2, "to": 2, "say": 2, "goodbye": 2, "李安": 47, "今天": 1, "現場": 1, "驚喜": 1, "至極": 1, "片子": 11, "越来越": 4, "升仙": 1, "感觉": 11, "世界": 15, "太美": 5, "见证": 1, "上帝": 9, "说辞": 1, "真是": 8, "羡慕": 1, "信仰": 41, "男主角": 1, "虽然": 10, "放开": 2, "一些": 6, "事物": 3, "但是": 15, "时候": 11, "还是": 13, "道别": 5, "然后": 8, "5.0": 1, "什么": 14, "看得见": 1, "之美": 2, "末日": 2, "无惧": 1, "蓝鲸": 1, "涌出": 1, "海面": 6, "如此": 4, "迫于": 1, "抢救": 1, "食物": 1, "无暇": 1, "欣赏": 2, "即便": 1, "抛开": 1, "3D": 52, "照样": 1, "美妙": 1, "故事": 77, "李安再": 2, "商业": 2, "光辉": 2, "对视": 1, "深海": 4, "一幕": 2, "合而为一": 1, "浮尸": 1, "同一": 1, "两种": 1, "讲法": 1, "照应": 1, "梦境": 3, "现实": 9, "到头来": 2, "不停": 2, "一台": 1, "灣人以": 1, "歐美人": 1, "眼鏡": 1, "視角講": 1, "印度人": 2, "動物": 1, "海上": 10, "事兒": 1, "除了": 4, "投合": 1, "消費": 1, "能力": 2, "各族人民": 1, "口味": 1, "意圖": 1, "很多": 14, "實在": 1, "看不出": 2, "這樣": 3, "有什麼": 1, "意義": 2, "招牌": 2, "似的": 1, "溫情": 1, "肆意": 1, "毫無節制": 1, "特效": 12, "美術": 1, "設計": 1, "二手": 1, "日本": 1, "一問": 1, "知道": 11, "原來": 1, "出自": 1, "寶島": 1, "人員": 2, "手筆": 1, "以为": 4, "它会": 1, "回头": 3, "只是": 11, "朝着": 1, "森林": 1, "深处": 1, "望去": 1, "永远": 6, "消失": 1, "也许": 5, "父亲": 1, "说得对": 1, "根本": 2, "没有": 33, "当成": 1, "非常": 8, "确定": 1, "眼中": 1, "看到": 20, "绝对": 8, "自己": 22, "目光": 2, "投射": 1, "倒影": 1, "那么": 9, "内心深处": 2, "不得不": 2, "承认": 5, "一样": 7, "电影": 71, "有个": 1, "吸引": 3, "开头": 2, "中间": 2, "开始": 10, "乏力": 1, "大段": 2, "重复": 3, "明信片": 2, "场景": 5, "呼唤": 1, "神灵": 5, "妈妈": 2, "至于": 2, "所谓": 5, "黑暗": 2, "这种": 4, "表面": 1, "直接": 3, "扔给": 1, "倾听": 1, "选择": 13, "方法": 1, "真的": 20, "独到": 1, "哪个": 6, "提升": 3, "感悟": 1, "反正": 1, "影响": 1, "不了": 1, "影片": 11, "失望": 5, "五星": 6, "献给": 1, "最好": 5, "可能": 6, "完成": 1, "任务": 1, "辛苦": 1, "努力": 2, "四年": 1, "终究": 1, "做到": 3, "第一次": 4, "感受": 5, "一部": 9, "不可分割": 1, "一部分": 1, "以及": 3, "变换": 1, "画幅": 2, "比例": 2, "层层": 1, "交替": 1, "剪辑": 2, "一切都是": 1, "为了": 3, "本身": 7, "冒险": 8, "有些": 11, "PI": 2, "其实": 13, "内心": 8, "表达": 4, "镜头": 12, "可以": 17, "从小": 2, "热爱": 3, "海洋": 2, "觉得": 15, "美极了": 3, "神秘": 2, "极了": 1, "完全": 11, "所能": 1, "想象": 4, "乘以": 1, "十倍": 1, "夸张": 1, "梦幻": 2, "勾勒": 1, "出来": 7, "水母": 4, "之夜": 1, "鲸鱼": 1, "出水": 1, "晚幕": 1, "晶莹剔透": 1, "绿色": 2, "孤岛": 2, "电闪雷鸣": 1, "暴风雨": 2, "等等": 1, "一帧": 3, "剪下来": 1, "一副": 1, "视觉": 10, "佳作": 1, "效果": 18, "异常": 2, "老虎": 17, "一下": 3, "我操": 2, "纽约": 2, "电影节": 1, "开幕": 1, "首映": 4, "唯一": 6, "画面": 20, "情节": 7, "紧凑": 1, "高潮": 1, "叠起": 1, "不是": 10, "再说": 1, "一遍": 2, "每个": 4, "渴望": 4, "美好": 14, "总是": 2, "无力": 1, "改变": 1, "残酷": 8, "唯有": 1, "调整": 1, "态度": 1, "方能": 1, "生活": 7, "寻得": 1, "一条": 1, "出路": 1, "穿透": 1, "漫天": 1, "乌云": 1, "一线": 1, "曙光": 1, "视为": 1, "神迹": 1, "我们": 18, "何尝": 1, "光明": 1, "憧憬": 1, "找到": 2, "前行": 3, "勇气": 1, "不断": 8, "过程": 2, "一天": 1, "能够": 3, "坦然": 1, "面对": 4, "生命": 7, "那些": 7, "遗憾": 2, "如影随形": 1, "好久": 1, "沒睡": 1, "那麼": 2, "電影": 5, "滿分": 1, "高考作文": 1, "一樣": 1, "沒什麼": 2, "意思": 1, "通篇": 1, "類似": 1, "那種": 1, "一個": 2, "人應": 1, "xx": 6, "應該": 2, "樣子": 1, "氣息": 1, "這些": 1, "終究": 1, "還是": 1, "命題": 1, "想講": 1, "東西": 2, "做成": 1, "這種": 1, "心靈雞": 1, "湯實": 1, "心中": 3, "一个": 52, "瑰丽": 4, "壮观": 2, "无人": 1, "能及": 1, "之旅": 3, "李安用": 3, "豪华": 1, "视效": 5, "最细挚": 1, "情感": 1, "打造": 1, "2012": 1, "荒野": 1, "生存": 4, "宁愿": 4, "一场": 5, "长醉": 1, "不醒": 1, "没能": 4, "震撼人心": 1, "不少": 1, "随便": 1, "几个": 4, "镜面": 2, "飞鱼": 5, "来袭": 1, "最强": 2, "之一": 3, "奄奄一息": 1, "那个": 13, "夜里": 1, "整个": 5, "影院": 5, "滴雨": 1, "抬头": 1, "是否是": 1, "天花板": 1, "漏水": 1, "同樣": 1, "是關": 1, "冒險": 1, "勝過": 1, "老馬": 1, "雨果": 3, "不止": 1, "一兩點": 1, "感覺": 1, "不再": 3, "商業": 1, "50": 1, "紐約": 1, "電影節": 1, "光榮": 1, "開幕": 1, "More": 1, "than": 2, "just": 2, "amazing": 1, "and": 1, "great": 1, "NYFF": 1, "开心": 1, "最后": 17, "买到": 1, "实在": 3, "好看": 5, "Memento": 1, "感到": 1, "再次": 1, "进步": 1, "不管": 3, "spiritual": 1, "technique": 1, "Mr": 1, "Parker": 2, "一顿": 2, "神奇": 3, "floating": 1, "island": 1, "海底": 1, "一眼": 2, "美爆": 1, "夜晚": 1, "好多好多": 1, "经典": 2, "眼泪": 2, "哗哗": 1, "李安打": 1, "通任督": 1, "二脉": 1, "确实": 3, "之树": 1, "....": 1, "有点": 7, "纺锤形": 1, "不过": 5, "对于": 8, "一只": 3, "漂了": 1, "将近": 2, "两个": 9, "小时": 2, "来说": 3, "全程": 2, "没尿点": 1, "无与伦比": 1, "之外": 2, "人虎间": 2, "化学反应": 2, "绚丽": 3, "炫耀": 1, "剧情": 3, "服务": 2, "片头": 1, "一片": 1, "惊呼": 1, "中段": 2, "更是": 4, "阵阵": 1, "而且": 4, "恐惧": 4, "基督": 2, "旷野": 1, "修炼": 1, "魔鬼": 2, "要求": 1, "展示": 2, "奇迹": 5, "石头": 1, "变成": 1, "面包": 1, "拒绝": 2, "诱惑": 1, "出现": 2, "第二个": 12, "版本": 2, "正是": 2, "印证": 2, "一点": 2, "主旨": 1, "反转": 1, "关于": 5, "确立": 1, "而是": 4, "缺失": 1, "不能": 4, "建立": 1, "之上": 1, "假如": 1, "悲哀": 3, "为什么": 4, "或者": 5, "原著": 8, "实际上": 1, "真相": 9, "血淋淋": 1, "告诉": 1, "这个": 15, "清醒": 1, "眼里": 2, "清楚": 4, "事实": 1, "没用": 1, "善良": 5, "稍微": 1, "不太": 1, "残忍": 10, "驯兽": 1, "自我": 3, "而已": 1, "最差": 3, "开场": 5, "动物": 11, "就让": 2, "这片": 1, "失去": 6, "信心": 2, "整部": 4, "毫无": 2, "节制": 1, "温情": 3, "台湾人": 1, "唠叨": 1, "加油": 1, "调调": 1, "卖萌": 1, "崩溃": 1, "使得": 2, "擅长": 1, "操作": 1, "成长": 2, "主题": 4, "停留": 2, "表层": 1, "既然": 1, "这么": 7, "为何": 3, "DISCOVERY": 1, "纪录片": 2, "他们": 5, "Imax": 1, "相当": 3, "并非": 1, "运用": 1, "炫目": 1, "炫技": 1, "视觉效果": 3, "合二为一": 1, "融为一体": 1, "美轮美奂": 1, "哲学": 3, "理性": 4, "完美": 4, "对话": 3, "孰真": 2, "重要": 5, "8.8": 1, "顿时": 1, "黯然": 1, "作为": 5, "合格": 1, "故事片": 1, "叙事": 3, "结构": 1, "乏味": 2, "至极": 1, "印度": 4, "殖民": 2, "背景": 1, "片中": 2, "显得": 1, "不伦不类": 1, "结束": 2, "处于": 1, "震惊": 2, "状态": 1, "难以相信": 1, "这是": 5, "相比之下": 1, "旁边": 1, "淡定": 1, "人家": 1, "撑过": 1, "激情": 1, "戏中": 1, "昏睡": 1, "过去": 2, "隐约": 1, "最大": 5, "认可": 1, "讲述": 3, "到达": 1, "高度": 1, "妥善": 1, "告别": 6, "汗颜": 1, "所有": 5, "华语": 1, "导演": 17, "李安現": 1, "畫面": 2, "越來": 1, "越美": 1, "內容": 1, "白話": 1, "...": 4, "這片": 1, "柏格曼": 1, "有關": 1, "媒体": 2, "亲自": 1, "讲话": 1, "随和": 1, "儒雅": 1, "沉稳": 1, "唯美": 5, "震撼": 13, "融合": 2, "发展": 1, "终于": 2, "没什么": 1, "坦言": 1, "生涯": 1, "一次": 8, "挑战": 2, "看来": 1, "结果": 3, "不错": 2, "国际": 1, "记者": 2, "报以": 1, "热烈": 1, "掌声": 1, "IMAX": 3, "体验": 2, "这部": 11, "无比": 2, "正确": 2, "决定": 1, "大气": 1, "技术": 6, "直指": 1, "巅峰": 1, "不急": 1, "不躁": 1, "前面": 3, "如同": 2, "画龙": 1, "一笔": 1, "美得": 2, "灵魂": 2, "出窍": 1, "一带而过": 1, "却是": 1, "点睛之笔": 1, "原来": 2, "好比": 1, "撒旦": 1, "附体": 1, "丑陋": 2, "喜欢": 12, "是不是": 2, "肤浅": 1, "矫情": 2, "哪里": 1, "昏昏欲睡": 2, "这样": 8, "制作": 2, "水准": 2, "好意思": 1, "票价": 1, "国产": 1, "画皮": 1, "怎么": 6, "一项": 2, "恶心": 1, "发明": 1, "大团结": 1, "一家亲": 1, "欢迎": 1, "李安来": 1, "中国": 2, "春节": 1, "联欢晚会": 1, "谢谢": 1, "相对": 2, "期待": 7, "落差": 1, "很大": 2, "前段": 1, "后段": 1, "填鸭式": 1, "腻味": 1, "过于": 2, "形式主义": 1, "造作": 1, "产生共鸣": 1, "所说": 3, "精美": 1, "还好": 1, "大家": 3, "分数": 1, "这次": 2, "同时": 2, "最美": 2, "恐怖": 4, "形容": 1, "又名": 1, "食尸": 1, "很水": 1, "之前": 3, "高端": 1, "冷艳": 1, "起码": 1, "inception": 1, "里头": 1, "到底": 5, "几层": 1, "忘个": 1, "差不多": 1, "大概": 2, "应该": 3, "还会": 1, "记得": 1, "夜光": 1, "打扮": 1, "仿佛": 1, "极夜": 1, "般的": 2, "要信": 1, "所述": 1, "好像": 3, "一则": 1, "寓言": 3, "目标": 1, "一段": 4, "传说": 3, "跟书里": 1, "部分": 5, "沉闷": 1, "熬过": 1, "惊险": 1, "随之": 1, "展开": 1, "蓝色": 1, "白色": 1, "小船": 2, "黄色": 1, "艳丽": 1, "看过": 6, "小说": 7, "仍会": 1, "感动": 3, "无懈可击": 1, "李安将": 1, "艺术": 1, "精神": 2, "内核": 1, "层面": 3, "PS": 1, "豆瓣": 2, "过分": 1, "解读": 1, "破坏": 1, "意境": 1, "请问": 1, "联想": 1, "食母": 1, "心理": 2, "阴暗": 1, "畸形": 1, "缺少": 2, "民族": 2, "钻牛角尖": 1, "答案": 3, "德性": 1, "多年": 1, "教育": 1, "制度": 1, "年度": 3, "第一": 1, "铺垫": 2, "必要": 1, "沉船": 3, "奇妙": 2, "通片": 1, "有意思": 1, "巧妙": 1, "展现": 3, "调度": 1, "按理说": 1, "更难": 1, "安叔": 3, "见安叔": 1, "印象": 4, "最深": 1, "跳到": 1, "水里": 2, "远处": 1, "转身": 1, "游回去": 1, "本年度": 2, "必看": 1, "人类": 3, "工业": 1, "极限": 1, "之作": 4, "李安对": 1, "多元": 1, "文化": 2, "特质": 1, "灵性": 1, "拿捏": 1, "人性": 11, "纯正": 1, "精髓": 1, "细致": 2, "提炼": 2, "庞大": 1, "寓意": 1, "更具": 1, "冲击力": 1, "影像": 3, "载体": 1, "blue": 1, "blah": 1, "工具": 2, "不会": 6, "真正": 4, "借口": 1, "或是": 1, "绊脚石": 1, "梦想": 2, "希望": 12, "信念": 1, "一切": 5, "东西": 8, "还有": 6, "似是而非": 1, "谈不上": 1, "表达出来": 1, "绝望": 1, "美国": 1, "平庸": 2, "结尾": 7, "神来之笔": 1, "悔罪": 1, "若干": 1, "只有": 7, "亲其神": 1, "信其道": 1, "心境": 2, "平和": 1, "信众": 1, "一家": 1, "经过": 2, "考验": 1, "才能": 3, "显现": 1, "力量": 4, "第一回": 1, "3d": 4, "喧宾夺主": 1, "束之高阁": 1, "全权": 1, "寻找": 1, "恢复": 1, "思考": 2, "衰老": 1, "不成形": 1, "杰拉尔": 1, "德帕迪": 1, "心儿": 1, "真心": 5, "哪儿": 1, "如果": 6, "睡着": 2, "有人": 3, "比较": 2, "阿凡": 3, "一知半解": 1, "不相上下": 1, "完爆": 1, "期望": 2, "以至于": 1, "整天": 1, "烂片": 1, "逐渐": 1, "丧失": 2, "星半": 1, "心情": 1, "宁静": 1, "上辈子": 1, "罪孽深重": 1, "这辈子": 1, "赎罪": 1, "总有一天": 1, "我会": 2, "尝试": 2, "放逐": 1, "Pi": 11, "船上": 2, "居然": 2, "笑声": 1, "只配": 1, "共产党": 1, "照耀": 1, "果然": 1, "讲故事": 2, "东方": 1, "思维": 1, "西方": 2, "认识": 2, "东亚人": 1, "面孔": 2, "保障": 1, "亚太": 1, "区域": 1, "票房": 1, "交流": 1, "满足": 1, "熟识": 1, "猎奇": 1, "琐碎": 1, "地为": 1, "点题": 1, "最终": 4, "突然": 1, "升华": 1, "主线": 2, "以后": 1, "走进": 2, "活在": 1, "童话": 3, "未尝": 1, "一种": 3, "特别": 5, "一則": 1, "自然": 3, "極佳": 1, "視覺": 1, "做出": 1, "呼應": 1, "棒極": 1, "超越": 3, "精采": 1, "拍成": 2, "李安導": 1, "演太": 1, "厲害": 1, "心灵鸡汤": 2, "估计": 1, "不入流": 1, "震得": 1, "七零八落": 1, "鸡皮疙瘩": 2, "127": 1, "分钟": 4, "已经": 4, "大旗": 1, "虎皮": 1, "窗户": 1, "镜子": 1, "确知": 2, "周长": 1, "半径": 1, "圆周率": 1, "无限": 4, "循环": 2, "无理数": 2, "测度": 1, "圆里": 1, "脱离": 1, "开去": 1, "陷入": 2, "穷尽": 1, "计算": 1, "亿兆": 1, "尾数": 1, "无法": 9, "得到": 2, "完整": 1, "延伸": 1, "......": 1, "美到": 2, "摒住": 1, "呼吸": 1, "imax3d": 1, "一分钟": 1, "个川香": 1, "双层": 1, "鸡腿": 1, "进影院": 1, "检票员": 1, "喊道": 1, "急个": 1, "回答": 1, "来看": 2, "pi": 2, "电影片": 1, "个堡": 1, "后面": 2, "忘记": 2, "汉堡": 1, "这茬": 1, "台词": 2, "好棒": 3, "其他": 3, "39370": 1, "短评": 1, "说完": 1, "疑问": 3, "问题": 4, "伴随": 1, "不同": 2, "历程": 2, "命运": 1, "何其相似": 1, "有太多": 1, "无能为力": 1, "意料之外": 1, "归途": 1, "镜海": 1, "星河": 1, "如何": 6, "划清": 1, "界限": 1, "明白": 4, "令人": 7, "难过": 1, "道別": 1, "旅程": 3, "殊途同归": 1, "孤独": 5, "一生": 2, "功课": 1, "连续": 1, "杀人": 2, "事件": 2, "浪漫": 1, "一面": 3, "本质": 3, "不乏": 1, "发达": 1, "帮助": 1, "自由": 1, "成为": 4, "叙述": 2, "此时": 1, "作用": 2, "日益": 1, "强大": 2, "创造": 1, "地域": 1, "充满": 2, "悲悯": 1, "大师": 2, "好莱坞": 2, "妥协": 1, "多余": 1, "评分": 3, "忍不住": 3, "两星": 1, "抱歉": 1, "绝美": 1, "窒息": 2, "个人": 4, "嘴里": 1, "宇宙": 3, "再来": 1, "赵忠祥": 1, "齐活": 1, "涤荡": 1, "Come": 1, "on": 1, "长颈鹿": 1, "成功": 2, "一般": 3, "归来": 2, "我想": 1, "打六星": 1, "李安说": 1, "要会": 1, "否则": 1, "像是": 2, "延续下去": 1, "讲完": 1, "就要": 1, "懂得": 1, "再见": 3, "冲着": 1, "九分": 1, "发现": 2, "弱化": 1, "思辨": 1, "冲突": 1, "不知": 2, "所踪": 1, "其他人": 1, "一定": 3, "原书": 1, "适合": 1, "改编": 2, "心态": 2, "不枉": 1, "赞死": 1, "表示": 1, "满意": 3, "太沉重": 1, "可是": 2, "后来": 1, "重新": 1, "拾起": 1, "摧毁": 1, "纯真": 6, "我祝": 1, "永不": 2, "吳同學": 1, "走出": 2, "兩個": 1, "回到": 2, "家裡": 1, "還沒有": 1, "千言": 1, "萬語": 1, "表達": 1, "然後我": 1, "這是": 1, "充滿": 2, "勇氣": 1, "外表": 2, "平靜溫": 1, "勇敢": 2, "挑戰": 1, "導演": 1, "帶給": 1, "愛電影": 1, "太棒了": 2, "进入": 1, "影史": 1, "前十了": 1, "不仅": 2, "结局": 4, "接近": 1, "真实": 8, "三个": 1, "个体": 1, "兽性": 5, "神性": 4, "排列组合": 1, "鱼群": 1, "莹莹": 1, "腾空而起": 1, "星空": 3, "映照": 1, "几乎": 1, "下来": 4, "桌面": 1, "那一岛": 1, "哈哈哈": 2, "哈哈": 1, "萌死个": 1, "亲爹": 1, "阿三": 2, "英语": 3, "骚力": 2, "啊哈": 1, "哈哈哈哈": 1, "一望无际": 1, "大海": 2, "木有": 1, "景深": 1, "不点": 1, "为止": 1, "作家": 3, "水手": 1, "斑马": 1, "话会": 1, "当然": 1, "老师": 2, "学生": 1, "代表": 1, "夜景": 1, "雨景": 1, "教科书": 1, "级别": 1, "小事儿": 1, "处理": 1, "然则": 1, "最近": 2, "两部": 1, "片儿": 1, "极其": 1, "十五分钟": 1, "四星": 1, "温柔": 2, "刹那之间": 1, "屁滚尿流": 1, "所以": 5, "残杀": 1, "大篇幅": 1, "很快": 1, "发生": 2, "剩下": 1, "长达": 1, "斗争": 2, "读过": 1, "心存": 1, "疑虑": 2, "打消": 1, "克里希纳": 1, "张开嘴": 1, "从中": 1, "这场": 2, "伏笔": 1, "最牛": 1, "地方": 4, "在于": 1, "明明": 2, "骗人": 1, "游戏": 1, "产生": 2, "谎言": 1, "暴露": 1, "真空": 1, "任何": 2, "心思": 1, "洞穿": 1, "赤诚": 1, "才华": 1, "缺一不可": 1, "够格": 1, "洗礼": 1, "下层": 1, "分布": 1, "舒适": 1, "命题": 2, "排布": 1, "结合": 1, "天衣无缝": 1, "动人": 2, "李安將": 1, "漫長": 1, "歷程": 1, "以視": 1, "覺化": 1, "手法": 2, "化成": 1, "層次": 1, "分明": 1, "遺憾": 1, "覺得": 1, "正面": 2, "一點": 2, "本來": 1, "會有": 1, "黯黑": 1, "出現": 1, "不過": 1, "這段": 1, "從書到": 1, "還有": 1, "參與": 1, "這部片": 2, "工作": 1, "作者": 1, "或許": 1, "強大": 1, "能量": 2, "格林童话": 1, "背后": 2, "凶残": 1, "野蛮": 1, "带来": 1, "远比": 1, "深刻": 4, "眼睛": 1, "生动": 2, "阿爸": 1, "那样": 3, "反射": 1, "投影": 1, "愿意": 1, "后者": 1, "相通": 1, "竟然": 3, "回地": 1, "走掉": 1, "心灰意冷": 1, "地想": 2, "这时候": 1, "李安带": 1, "想想": 1, "三颗": 1, "五颗星": 1, "海景": 3, "水下": 2, "美景": 4, "壮丽": 3, "再现": 2, "片能": 2, "可非": 2, "文艺": 2, "宗教": 5, "刻意": 2, "生硬": 2, "胃口": 2, "吊得": 2, "很足": 2, "粗劣": 2, "深度": 3, "何必": 4, "深沉": 2, "故意": 2, "迎合": 3, "大众": 2, "心有": 2, "时而": 1, "家庭": 3, "三部曲": 2, "断背山": 2, "色戒": 1, "无非": 1, "选择性": 2, "记忆": 1, "遗忘": 2, "方式": 2, "而生": 1, "而病": 1, "开放": 1, "诠释": 2, "留给": 1, "用来": 2, "战胜": 2, "相处": 2, "不合理": 2, "必须": 5, "它们": 1, "牢固": 1, "依靠": 2, "七分": 1, "值得一看": 1, "把握": 1, "节奏": 3, "不佳": 1, "自言自语": 1, "9.1": 1, "显然": 1, "过誉": 1, "尽快": 1, "认为": 2, "讨论": 2, "数度": 1, "高呼": 1, "不知所云": 1, "何解": 1, "一本": 2, "不可思议": 3, "不到": 1, "更好": 2, "由于": 1, "存在": 4, "本片": 3, "史上": 1, "最棒": 2, "名号": 1, "附有": 1, "大量": 1, "旁白": 1, "韵味": 1, "不足": 1, "突出": 2, "有失": 1, "尤其": 2, "imax": 2, "那种": 1, "享受": 3, "形式": 1, "无法比拟": 1, "深夜里": 1, "漂浮": 1, "平静": 2, "闪烁着": 1, "银光": 1, "第一遍": 1, "观影": 2, "隐隐": 1, "隐喻": 4, "主要": 1, "其中": 1, "想象力": 1, "无论": 2, "一半": 1, "言过其实": 1, "张艺谋": 1, "漂亮": 4, "争论": 1, "辨析": 1, "毫无意义": 1, "强化": 1, "120": 1, "信者": 2, "甚少": 1, "疑者": 1, "甚多": 1, "于是": 1, "只得": 1, "再花": 1, "交差": 1, "多数": 1, "毫不犹豫": 1, "正因": 1, "第一个": 6, "模样": 1, "认清": 1, "本性": 2, "时刻": 1, "很棒": 2, "场面": 1, "小岛": 2, "究竟": 1, "与其说是": 1, "倒不如说": 1, "交杂": 1, "幻化": 1, "倾诉": 1, "海报": 2, "简直": 2, "错过": 1, "鹌鹑": 1, "出埃及记": 1, "妖魔": 1, "妖岛": 1, "奥德赛": 1, "神棍": 1, "鲁宾孙": 1, "星期五": 1, "沉前": 1, "人会": 1, "满面": 1, "厌烦": 1, "拖沓": 3, "不堪": 1, "总之": 2, "一锅": 1, "普通人": 1, "情结": 1, "冯小刚": 2, "相比": 1, "李安要": 1, "一百个": 1, "陆川": 1, "距离": 1, "没差": 1, "多少": 1, "缺乏": 1, "训练": 1, "导致": 1, "部落": 1, "神祗": 2, "粗糙": 1, "具体": 1, "神及": 1, "相关": 1, "迷信": 1, "胸中": 1, "形成": 1, "体察": 1, "重量": 1, "始终": 3, "技巧": 2, "佩服": 6, "于心不忍": 1, "可见": 1, "共通": 1, "可视": 1, "某些": 1, "方面": 2, "远远": 1, "隐不隐": 1, "工于": 1, "宽容": 1, "下意识": 1, "提前": 1, "离场": 1, "音乐": 1, "字幕": 1, "精致": 2, "平实": 1, "强烈推荐": 1, "高三": 1, "哭成": 1, "dog": 1, "墨迹": 1, "信奉": 2, "诸神": 1, "众多": 1, "之中": 2, "不离": 1, "不弃": 1, "便是": 1, "彼此": 1, "只要": 1, "召唤": 1, "从不": 2, "迟到": 1, "隐匿": 1, "无穷": 1, "三星": 3, "壮美": 1, "摄人心魄": 1, "孩子气": 1, "孩子": 2, "痛苦": 4, "气愤": 1, "深深": 1, "依恋": 1, "说教": 2, "味道": 1, "浓重": 1, "太过": 1, "直白": 1, "掩饰": 1, "不住": 1, "急于": 1, "传教": 1, "全部": 1, "零分": 2, "混乱": 1, "景观": 1, "可观": 1, "后悔": 1, "赶时髦": 1, "4d": 1, "一股": 1, "咖喱": 1, "味儿": 2, "雨水": 1, "哎呀呀": 1, "沉浸于": 1, "深陷": 1, "疑团": 1, "事情": 1, "风格": 2, "表现": 3, "大自然": 2, "那份": 2, "坚持": 2, "截取": 1, "片段": 1, "冷酷": 1, "实际": 1, "远不如": 1, "预告片": 1, "Hobbit": 1, "重量级": 1, "差异": 1, "无波": 1, "出戏": 1, "魔幻": 1, "表述": 1, "半度": 1, "倾向": 1, "糖水": 1, "童话故事": 1, "飞跃": 1, "中庸": 1, "3.5": 2, "奇观": 4, "只能": 3, "对得起": 1, "高分": 1, "细思极": 1, "影评": 1, "解析": 1, "越发": 1, "励志": 1, "明显": 2, "更加": 1, "悉心": 1, "驯养": 1, "未知": 2, "可能性": 2, "倾入": 1, "时间": 1, "性命": 1, "所求": 1, "顾及": 1, "年少": 1, "无关": 1, "尚且": 1, "回想起来": 1, "当时": 1, "多么": 1, "摧枯拉朽": 1, "顷尽": 1, "机会": 1, "说声": 1, "含义": 2, "尼玛": 1, "单调": 1, "内容空洞": 1, "饱满": 1, "你们": 1, "忽悠": 1, "两颗": 1, "少有": 1, "预告": 1, "难道": 2, "仅仅": 1, "华丽": 1, "男人": 2, "唠嗑": 1, "20": 1, "蛋疼": 1, "剧本": 2, "普通": 2, "一个男孩": 1, "穿越": 1, "太平洋": 2, "噱头": 2, "不要": 3, "抱太高": 1, "分析": 2, "天堂": 1, "李安造": 1, "幻梦": 1, "掩卷": 1, "叹息": 1, "回味": 2, "幸运": 1, "出合心": 1, "筑梦师": 1, "superhero": 1, "厅里": 1, "堪称": 1, "视听": 1, "盛宴": 2, "忠实": 1, "原作": 3, "许多": 1, "温润": 1, "反映": 1, "用力": 1, "太蛮": 1, "不可": 1, "反倒": 1, "抒情": 1, "达到": 1, "今年": 1, "奥斯卡": 3, "不在话下": 1, "目前": 1, "仅能": 1, "蝙蝠侠": 2, "技术奖": 1, "可靠": 1, "看一遍": 1, "维度": 1, "一时间": 1, "很少": 1, "需要": 3, "iMax": 1, "影厅": 1, "去一趟": 1, "直到": 2, "缓缓": 1, "给出": 2, "包装": 1, "美的": 1, "之下": 1, "连环": 1, "怀疑": 1, "一体": 1, "两面": 1, "拍会": 1, "教坏": 1, "小朋友": 2, "透过": 1, "另一面": 1, "邪恶": 4, "孰是孰非": 1, "理查德": 4, "搏击": 1, "俱乐部": 1, "鲁宾逊": 1, "漂流记": 1, "惊悚片": 1, "风景": 2, "虔诚": 2, "信仰者": 1, "面前": 1, "挣扎": 2, "崩塌": 1, "寥寥": 1, "几句": 1, "营养": 1, "大片": 1, "正反两面": 1, "religion": 1, "God": 2, "某种程度": 1, "化身": 1, "视之为": 1, "奇遇": 1, "淬炼": 1, "因此": 1, "改写": 1, "环境": 1, "最难": 2, "外化": 1, "由此": 1, "着意": 1, "减少": 1, "趣味性": 1, "探索": 2, "层次": 1, "第一节": 1, "流畅": 1, "幽默": 1, "二三": 1, "沉重": 1, "或许": 3, "特调": 1, "不合": 1, "一次次": 1, "违背": 1, "最为": 2, "讽刺": 1, "拯救": 2, "可怕": 1, "抛之脑": 1, "原始": 1, "共舞": 1, "食人岛": 1, "犯罪": 1, "映射": 1, "羞于": 1, "忏悔": 1, "人性本恶": 1, "一起": 2, "铭记": 2, "恶劣": 1, "自然环境": 1, "吞噬": 1, "更让人": 1, "抓狂": 1, "一颗": 3, "寸步难行": 1, "汪洋": 1, "孤舟": 1, "作陪": 1, "迄今为止": 2, "美丽": 2, "永存": 1, "壮阔": 1, "委婉": 1, "感人": 1, "细腻": 2, "抢戏": 1, "新世纪": 1, "银幕": 3, "商人": 1, "手里": 2, "道具": 1, "封神": 1, "一地": 1, "缺憾": 1, "海浪": 1, "逼真": 2, "看得": 1, "晕船": 1, "科学": 1, "比如": 3, "诗意": 1, "Richard": 1, "tiger": 1, "in": 1, "my": 1, "heart": 1, "不该": 1, "权力": 1, "手中": 1, "怎样": 3, "心知肚明": 1, "追随": 1, "肯定": 1, "东西方": 1, "双重": 1, "智慧": 1, "程度": 1, "还原": 1, "追求": 3, "精巧": 1, "一头": 1, "期盼": 1, "坚强": 1, "一一": 1, "刻画": 1, "魄力": 1, "发人深省": 1, "画面感": 1, "好强": 1, "卧虎藏龙": 2, "断臂山": 1, "突破": 1, "从未": 1, "舍弃": 1, "招牌式": 1, "肆虐": 1, "这点": 1, "学学": 1, "金馬": 1, "影展": 1, "加場": 1, "西门町": 1, "国宾": 1, "大戏院": 1, "现场": 1, "色彩": 1, "明丽": 1, "人物": 2, "简单": 2, "宗教信仰": 1, "人与自然": 1, "关系": 3, "探究": 1, "表面化": 1, "不温不火": 1, "中规中矩": 1, "甚至": 3, "乏善可陈": 1, "此片": 1, "考量": 1, "轴线": 1, "内外": 1, "延展": 1, "价值": 1, "回来": 1, "赶紧": 1, "在读": 1, "仍旧": 1, "提到": 1, "男孩": 2, "对应": 1, "真实世界": 1, "臆想": 1, "探讨": 1, "过时": 1, "niki": 1, "一口": 1, "砰砰": 1, "来到": 1, "满是": 1, "yoga": 1, "狡猾": 1, "荒岛": 1, "余生": 1, "不比": 1, "拍三大": 1, "要素": 1, "小孩": 1, "全拍": 1, "水拍": 1, "听说": 1, "电脑": 1, "特技": 1, "中水": 1, "运算": 1, "复杂": 1, "拍水": 1, "前半段": 1, "压抑": 1, "繁琐": 1, "后半段": 1, "綺丽": 1, "三观": 1, "毋庸置疑": 1, "最佳影片": 1, "说实话": 1, "惊讶": 1, "全程无": 1, "尿点": 1, "回家路上": 1, "接下来": 1, "配乐": 1, "观感": 1, "归于": 1, "国内": 2, "太小": 1, "太暗": 1, "德基": 1, "二期": 1, "装好": 1, "跟井去": 1, "一刷": 1, "妹子": 1, "世纪": 1, "电脑城": 1, "二刷": 1, "意味深长": 1, "可惜": 2, "完图": 1, "晚上": 1, "太累": 1, "困死": 1, "罪过": 1, "口音": 1, "听不懂": 1, "喜不喜欢": 1, "壁纸": 1, "只放": 1, "星期": 1, "太赞": 1, "上映": 1, "普适": 1, "真理": 1, "活着": 1, "的话": 1, "差评": 1, "迷上": 1, "好评": 2, "读出": 1, "空落落": 1, "理解": 3, "接受": 1, "脆弱": 1, "装小": 1, "清新": 1, "穆赫兰道": 1, "失语": 1, "深层": 1, "捉摸不透": 1, "橙天": 1, "嘉禾": 1, "壹街": 1, "影城": 1, "纳尼亚": 1, "传奇": 1, "合家欢": 1, "满场": 1, "哇哇地": 1, "梦幻般": 1, "并且": 1, "这般": 1, "功力": 1, "莫名": 1, "想起": 1, "那句": 2, "感兴趣": 1, "剧集": 1, "指向": 1, "论断": 1, "好事儿": 1, "动情": 1, "整出": 1, "剧透太多": 1, "折损": 1, "一星": 1, "第二": 2, "更爱": 1, "事关": 1, "文学": 2, "记住": 1, "逆境": 1, "警醒": 1, "鞭策": 1, "李安在": 1, "灰白": 1, "社会": 2, "之心": 1, "否定": 1, "最佳": 1, "今晚": 1, "做梦": 1, "见到": 1, "丛林": 1, "入口": 1, "转头": 1, "办法": 1, "和平共处": 1, "不如": 1, "ps": 2, "百分之": 1, "70": 1, "完会": 1, "回家": 1, "一把": 1, "香蕉": 1, "放进": 1, "一泡": 1, "是因为": 3, "直观": 1, "的确": 1, "想错": 1, "不管怎么": 1, "没看": 1, "代入": 1, "象征": 1, "戴着": 1, "眼镜": 1, "静心": 1, "依然": 1, "内敛": 1, "做作": 1, "派对": 1, "现在": 3, "爸爸妈妈": 1, "哥哥": 1, "向前": 1, "分别": 1, "认真": 1, "回忆": 2, "编成": 1, "继续": 1, "部类": 1, "神片": 1, "拿个": 1, "被动": 1, "剧透": 2, "杀死": 2, "几多": 1, "乐趣": 1, "信息": 1, "视觉享受": 1, "推荐": 1, "美哇": 1, "长队": 1, "一如": 1, "两场": 1, "饭桌": 1, "岁月": 3, "突显出": 1, "主人公": 1, "人生观": 1, "进化": 1, "妇联": 1, "轰炸机": 1, "寄情": 1, "于景": 1, "效能": 1, "斩获": 1, "利刃": 1, "好萌": 1, "入党": 1, "道路": 1, "不僅僅": 1, "前途": 1, "奢侈": 1, "安好": 1, "happy": 1, "ending": 1, "有关": 1, "怎么样": 1, "符号": 1, "暗喻": 1, "明喻": 1, "诚如": 1, "人们": 1, "读解": 1, "不曾": 1, "想到": 1, "感谢": 1, "圣经": 1, "亚伯拉罕": 1, "重现": 1, "王柏": 1, "杰出": 1, "各种": 1, "酱油": 1, "吸引力": 1, "衔接": 1, "赋予": 1, "其本": 1, "具有": 1, "深刻反思": 1, "似乎": 2, "体现": 1, "局限性": 1, "推敲": 1, "改成": 1, "不让": 1, "放弃": 1, "宝贵": 1, "高峰": 1, "中文": 1, "译名": 1, "绮丽": 1, "多彩": 1, "海难": 1, "戏快": 1, "几度": 1, "走神": 1, "冗长": 1, "揭示": 1, "意义": 1, "Life": 1, "should": 1, "be": 1, "so": 1, "much": 1, "more": 1, "surviving": 1, "敌人": 1, "值得": 2, "无数遍": 1, "对安叔": 1, "五体投地": 1, "小时候": 1, "这类": 1, "探险": 1, "冒险类": 1, "厨师": 1, "保留": 1, "一丝": 1, "经历": 2, "这些": 1, "无忧无虑": 1, "包围": 1, "宁可": 1, "抱怨": 1, "五分": 1, "美奂": 1, "绝伦": 1, "一名": 2, "勇士": 1, "双面": 1, "身体": 1, "会作": 1, "殊死": 1, "外界": 1, "压力": 1, "掩藏": 1, "和谐": 1, "掩盖": 1, "没法": 1, "尽量": 1, "打分": 1, "大猫": 1, "呜呜": 2, "饿瘦": 1, "完后": 1, "讨厌": 1, "三三": 1, "吵死": 1, "香港": 1, "看電影": 1, "沒話": 1, "好劇": 1, "情佳": 1, "推薦": 1, "特么": 1, "奇好": 1, "身临其境": 1, "打动": 1, "李导": 1, "美帝": 1, "字原": 1, "鸭梨": 1, "黑咕隆咚": 1, "播放": 1, "浪费": 1, "可贵": 1, "永保": 1, "即使": 1, "随着": 1, "流逝": 1, "消退": 1, "保有": 1, "怀念": 1, "赤子之心": 1, "几次": 1, "变化": 1, "16": 1, "关注": 1, "细节": 1, "题材": 1, "他妈": 1, "少儿": 1, "益智": 1, "请原谅": 1, "水平": 1, "光顾": 1, "深层次": 1, "第二遍": 1, "挖掘": 1, "哭哭啼啼": 1, "絮絮叨叨": 1, "略显": 1, "多话": 1, "被吸入": 1, "动弹不得": 1, "目眩神迷": 1, "从头到尾": 1}